[
  {
    "timestamp": 1730156095,
    "date": "2024-10-28 15:54:55",
    "token_amount": 2602016.773101,
    "sol_amount": 0.072930329,
    "price_in_sol": 2.8028385425465177e-08,
    "price_in_usd": 4.961024220307336e-06,
    "market_cap": 4961.024220307337,
    "signature": "5XB5hqfNqmJeWTdd5ZMJUAkqD4gWF3JUHzZeNJngULrsSAYRULzX19HdNDaAD834U3ZAfw9D4Ha1RUUgX7wvicAY"
  },
  {
    "timestamp": 1730155252,
    "date": "2024-10-28 15:40:52",
    "token_amount": 530618.098379,
    "sol_amount": 0.014915917,
    "price_in_sol": 2.8110456551646186e-08,
    "price_in_usd": 4.975550809641375e-06,
    "market_cap": 4975.550809641375,
    "signature": "3wbKD7quWgMYyttwCcWvXwtJQ9xBSc9nEPxTsr2JivvUjiHXfFrXwTDfKFEaJyqVwNgg7qmoAAS9jCUfcqoyU9kn"
  },
  {
    "timestamp": 1730155180,
    "date": "2024-10-28 15:39:40",
    "token_amount": 7875285.709538,
    "sol_amount": 0.223130177,
    "price_in_sol": 2.8332962793941588e-08,
    "price_in_usd": 5.0149344145276614e-06,
    "market_cap": 5014.934414527662,
    "signature": "44UmFV6d2xoRrkcp59DTbpYtzjFML5UoDbwVHFqPUNjjCtsk4B1BsxyPnTCxGSNErFN5srZK3QqGbQzbB6twCUJp"
  },
  {
    "timestamp": 1730155147,
    "date": "2024-10-28 15:39:07",
    "token_amount": 245016.968861,
    "sol_amount": 0.006995151,
    "price_in_sol": 2.8549659366524945e-08,
    "price_in_usd": 5.053289707874915e-06,
    "market_cap": 5053.289707874915,
    "signature": "5aqTaDbYcKnz3uFwu4ixGXhVAoE1AJCHaZ4wffwQ5oDjL88gs5wKvSvnfukG6A4AG4CAR44UuBuTUvmo5e2ADgnC"
  },
  {
    "timestamp": 1730155129,
    "date": "2024-10-28 15:38:49",
    "token_amount": 928477.681043,
    "sol_amount": 0.026537046,
    "price_in_sol": 2.8581242760935047e-08,
    "price_in_usd": 5.058879968685503e-06,
    "market_cap": 5058.879968685503,
    "signature": "GKrgbYFsh1hLnDG251dYF9TFMC2vm9pen3HMR1Ksj7ZdeRrrREojfAaoQA1Ah9fkc6JDz5wafiFw4MqNpZzqktS"
  },
  {
    "timestamp": 1730155123,
    "date": "2024-10-28 15:38:43",
    "token_amount": 2628299.77081,
    "sol_amount": 0.083551783,
    "price_in_sol": 3.178928976364468e-08,
    "price_in_usd": 5.626704288165109e-06,
    "market_cap": 5626.704288165109,
    "signature": "5FQUotsB57wHHHTd5SBCdiAGSiWQFyNcJXVcc1TtAbFTEpg9VTq5x1kso6VM8JnnW12tnh9uzo4tBvgtTgWaZpeT"
  },
  {
    "timestamp": 1730155118,
    "date": "2024-10-28 15:38:38",
    "token_amount": 1470030.046,
    "sol_amount": 0.041902374,
    "price_in_sol": 2.8504433711418166e-08,
    "price_in_usd": 5.045284766921015e-06,
    "market_cap": 5045.284766921015,
    "signature": "3wdvhV6oNZxXFFp9V4JWXUriTTni2theMKSkZiTV67fpYe2RVEte7sNkh3Y2qeGzUgMr4Rwantv7Zk5rqPDQqYWf"
  },
  {
    "timestamp": 1730155118,
    "date": "2024-10-28 15:38:38",
    "token_amount": 1225970.424,
    "sol_amount": 0.035034412,
    "price_in_sol": 2.8576881884060847e-08,
    "price_in_usd": 5.05810809347877e-06,
    "market_cap": 5058.10809347877,
    "signature": "54Jwt1QYwtJX62QQ3HrPuApnDH5X9cYTjv3J3Q1Vvc2A14fcZosSejnoGgKzRtXUfydwBcPmi9HUQVpUpGendXEH"
  },
  {
    "timestamp": 1730155118,
    "date": "2024-10-28 15:38:38",
    "token_amount": 848798.5449,
    "sol_amount": 0.024303499,
    "price_in_sol": 2.8632823590506133e-08,
    "price_in_usd": 5.068009775519585e-06,
    "market_cap": 5068.009775519586,
    "signature": "5YNmp8XSxEALy5wsQiCwX6Bpg2rUG49YiQVhXUCZSRPx94zCrmzhdinTvuCky6GFaZdG1Wj5n6fX9Hco7wGFSDHP"
  },
  {
    "timestamp": 1730155116,
    "date": "2024-10-28 15:38:36",
    "token_amount": 1980197.2731,
    "sol_amount": 0.056850261,
    "price_in_sol": 2.8709392630866964e-08,
    "price_in_usd": 5.081562495663453e-06,
    "market_cap": 5081.562495663453,
    "signature": "2kF6LdwNAUUBqVLDhc3GdPbPcCfk58gnyJRxY751gBmm1HDzbepHc1HZyRM642dZjxfLUNtANdGFGzfspVfMMg9V"
  },
  {
    "timestamp": 1730155115,
    "date": "2024-10-28 15:38:35",
    "token_amount": 4796729.7906,
    "sol_amount": 0.144547087,
    "price_in_sol": 3.0134506905780757e-08,
    "price_in_usd": 5.333807722323194e-06,
    "market_cap": 5333.807722323194,
    "signature": "3tWbpvhA58bTRShkdDtMJhAcWXzvrZX7UJL5BSPFA9eLS1ubhtFN4H4Pkbm57TpCJfgWTEu9FiTCcAhxPkTJC545"
  },
  {
    "timestamp": 1730155115,
    "date": "2024-10-28 15:38:35",
    "token_amount": 4640568.2258,
    "sol_amount": 0.158944208,
    "price_in_sol": 3.425102277697882e-08,
    "price_in_usd": 6.062431031525252e-06,
    "market_cap": 6062.431031525252,
    "signature": "3mnZnUQ4VKsuiY9dtFYcqSdsfEYYn6vzxWGn8SDHn4eMC9W3dg7k4Te7XMpiArqNEH9dhN2B7TprDR4vnF7oUkAU"
  },
  {
    "timestamp": 1730155115,
    "date": "2024-10-28 15:38:35",
    "token_amount": 3379844.7561,
    "sol_amount": 0.097526505,
    "price_in_sol": 2.8855320891287254e-08,
    "price_in_usd": 5.107391797757844e-06,
    "market_cap": 5107.391797757844,
    "signature": "61GBxZurrWtfXcTFhmSCDy4263oqCDMXsXcNs4yC17qCW4QqGLUTFk3teNnNkvZaTn3NooSHmEjj6GYiBBbebYBA"
  },
  {
    "timestamp": 1730155115,
    "date": "2024-10-28 15:38:35",
    "token_amount": 2255680.7463,
    "sol_amount": 0.075521004,
    "price_in_sol": 3.3480360252166594e-08,
    "price_in_usd": 5.926023764633487e-06,
    "market_cap": 5926.023764633487,
    "signature": "3QPB2eybZvsMSneSHTsm7sk64bHmxz96BGjdMe4yU6yesaFZw3YVRY8Srie9UCotfthugihGWnmG6EogQgXqMEYG"
  },
  {
    "timestamp": 1730155115,
    "date": "2024-10-28 15:38:35",
    "token_amount": 4898773.4306,
    "sol_amount": 0.161813164,
    "price_in_sol": 3.3031363114129815e-08,
    "price_in_usd": 5.846551271200977e-06,
    "market_cap": 5846.551271200977,
    "signature": "3Abib6DjrCkSsGPztAK8sFYdV8FCBahJZJg7D1FrBKGNVhqgz1anpK94JzuecBKmvSneX6Tin4HWRajkN2cecUSh"
  },
  {
    "timestamp": 1730155115,
    "date": "2024-10-28 15:38:35",
    "token_amount": 5969194.0552,
    "sol_amount": 0.18301558,
    "price_in_sol": 3.066001512223714e-08,
    "price_in_usd": 5.4268226766359735e-06,
    "market_cap": 5426.822676635973,
    "signature": "838SPkYCkpdcYDmX97XZ6Pt1ABXfyfUcf8UPZRpb6P43iqwbLbUFauuvTrMgUoCKHB69jFBLxEjcxjikqw3KV4s"
  },
  {
    "timestamp": 1730155115,
    "date": "2024-10-28 15:38:35",
    "token_amount": 3335939.0015,
    "sol_amount": 0.099740224,
    "price_in_sol": 2.989869537636988e-08,
    "price_in_usd": 5.292069081617469e-06,
    "market_cap": 5292.069081617469,
    "signature": "5Rsv8beBuQuQ7n2aAGDiVVnVaP6KxhvrDJuRjn6YfSB5LseWo49mdvgD1fyQJp2nF8KcBDDs71gaJDa6gKcJCt1x"
  },
  {
    "timestamp": 1730155115,
    "date": "2024-10-28 15:38:35",
    "token_amount": 3275674.5355,
    "sol_amount": 0.102478197,
    "price_in_sol": 3.128460898340063e-08,
    "price_in_usd": 5.5373757900619115e-06,
    "market_cap": 5537.375790061911,
    "signature": "3q1gViRexWfUxEs1ymdDQjeT3taPbFKkpYTa3BvFknrg6tJoP8WGymRPGQgnsWy5mYWSD3hdNUBw746qHiCGEMAP"
  },
  {
    "timestamp": 1730155115,
    "date": "2024-10-28 15:38:35",
    "token_amount": 2626242.7021,
    "sol_amount": 0.078071902,
    "price_in_sol": 2.9727603597935575e-08,
    "price_in_usd": 5.261785836834597e-06,
    "market_cap": 5261.785836834597,
    "signature": "31ReLqcgEQ3t7sqBwPCB52RQVAh6SQpuACcvPfUdgsLrpRy6sakWNJrg4YvV9RXWB3bhhQKXCFCyn1DSjaVL8mHt"
  },
  {
    "timestamp": 1730155115,
    "date": "2024-10-28 15:38:35",
    "token_amount": 5241997.567,
    "sol_amount": 0.166246208,
    "price_in_sol": 3.171428560870982e-08,
    "price_in_usd": 5.613428552741638e-06,
    "market_cap": 5613.428552741638,
    "signature": "4g4xTGq2zBwo3DRowQLueVYcxF4MyChn8TNFffmZGB7rUQqvGNS55ZBTWLJPUdcCRvAdT7erVKhZnJXmAUSd6LLg"
  },
  {
    "timestamp": 1730155115,
    "date": "2024-10-28 15:38:35",
    "token_amount": 2978927.2094,
    "sol_amount": 0.095249762,
    "price_in_sol": 3.197451810821007e-08,
    "price_in_usd": 5.6594897051531825e-06,
    "market_cap": 5659.4897051531825,
    "signature": "312y38ny98pQzXsgbpE8QpbL84hewxLPxPXSm7W9xqC8yxb87vHbWDm71BXQiyKk15558KtxtSu7sNgwGKZwev7H"
  },
  {
    "timestamp": 1730155115,
    "date": "2024-10-28 15:38:35",
    "token_amount": 3103278.1283,
    "sol_amount": 0.099830077,
    "price_in_sol": 3.2169232944224594e-08,
    "price_in_usd": 5.6939542311277535e-06,
    "market_cap": 5693.954231127754,
    "signature": "2MeGmHCBCiZNRucJCsH5fvmZ3WYbusxXzt9aDv1iUwZytM2vcKZDndRk9W8wj9SSGBvCGhZb1x6NaRUzkw2ifrb"
  },
  {
    "timestamp": 1730155115,
    "date": "2024-10-28 15:38:35",
    "token_amount": 3387626.1739,
    "sol_amount": 0.109687976,
    "price_in_sol": 3.2379008299408046e-08,
    "price_in_usd": 5.731084468995224e-06,
    "market_cap": 5731.084468995224,
    "signature": "A2KMMWZzqovyZMXHbGJW7RCx8bdRAojBWBAxYF7FQXbkTZHuL7gDYDM3kgqQaib9mHiTufd3L5xNTqMKkcPocq6"
  },
  {
    "timestamp": 1730155115,
    "date": "2024-10-28 15:38:35",
    "token_amount": 2634016.2269,
    "sol_amount": 0.082886283,
    "price_in_sol": 3.146764327171579e-08,
    "price_in_usd": 5.569772859093695e-06,
    "market_cap": 5569.772859093695,
    "signature": "3qHVxUr76WDr3YKVQBxkju521WPL9eVBTQ8Pd3dJ7VmSPcPW5ikt4dpf5gYSChY3R2SHTCJrcUQhN9HLFzRiH42M"
  },
  {
    "timestamp": 1730155115,
    "date": "2024-10-28 15:38:35",
    "token_amount": 3511142.6668,
    "sol_amount": 0.10666194,
    "price_in_sol": 3.0378127613142534e-08,
    "price_in_usd": 5.376928587526228e-06,
    "market_cap": 5376.9285875262285,
    "signature": "3BsBY6pqW4rjnB7Fwm1G8v1ootZv619WtHcxNzBqdVQFrrsxZcVkbxin75uydmsP2tnDcjXfEjr2sSnzhZJFHf8a"
  },
  {
    "timestamp": 1730155115,
    "date": "2024-10-28 15:38:35",
    "token_amount": 3066939.5576,
    "sol_amount": 0.102127231,
    "price_in_sol": 3.329939474905027e-08,
    "price_in_usd": 5.8939928705818985e-06,
    "market_cap": 5893.992870581898,
    "signature": "4KsQqmNBSCSZntjam3nMQr1rQEYmnpwCwV35DJBBVkRcWezU6qhYVF8d9vXZ1sKieETGFccJ8jtxqmQJj8CrPYCN"
  },
  {
    "timestamp": 1730155115,
    "date": "2024-10-28 15:38:35",
    "token_amount": 658986.6258,
    "sol_amount": 0.019528363,
    "price_in_sol": 2.963392918072177e-08,
    "price_in_usd": 5.245205464987754e-06,
    "market_cap": 5245.205464987754,
    "signature": "3yHJZYu8S1Hkdk8dAfZysMJzjFK4xHsedPxbPg5JRmD8aeMbVWLSjSubjccBAcnv6yzv1zDzGA4kEC9aLPQ7wwFS"
  },
  {
    "timestamp": 1730155115,
    "date": "2024-10-28 15:38:35",
    "token_amount": 4700017.4783,
    "sol_amount": 0.138567269,
    "price_in_sol": 2.9482288021218147e-08,
    "price_in_usd": 5.218364979755612e-06,
    "market_cap": 5218.364979755612,
    "signature": "5ytk6EZiegitNgEWhDrTjAkzCQzF5RkMSP2eJrLqKV6E8GQDD5PNobo76PwJ8hizXzB2c4eFys4NoEQPHApXWkm3"
  },
  {
    "timestamp": 1730155115,
    "date": "2024-10-28 15:38:35",
    "token_amount": 5750213.1688,
    "sol_amount": 0.18790536,
    "price_in_sol": 3.2677981578066185e-08,
    "price_in_usd": 5.784002739317714e-06,
    "market_cap": 5784.002739317714,
    "signature": "pHVLv19Vq7MtpwHisybXkmqpjzkhU2j7EtdpaYbNhasqUt737bCHDGzN3JxfPUmnhb4eU9oufm2durbPwWc5mVK"
  },
  {
    "timestamp": 1730155115,
    "date": "2024-10-28 15:38:35",
    "token_amount": 1862291.1734,
    "sol_amount": 0.054561175,
    "price_in_sol": 2.9297875530595588e-08,
    "price_in_usd": 5.185723968915419e-06,
    "market_cap": 5185.7239689154185,
    "signature": "3pFBzwknZBb9fAwEZTYBpWmUEhfWJBqyoBYQ2gMYzZ2ivhMHkcdfA97u5nUjpDp9vqmdZASzE7MzJyF7CqyLajBA"
  },
  {
    "timestamp": 1730155115,
    "date": "2024-10-28 15:38:35",
    "token_amount": 5387388.8451,
    "sol_amount": 0.156753923,
    "price_in_sol": 2.909645609534434e-08,
    "price_in_usd": 5.150072728875948e-06,
    "market_cap": 5150.072728875948,
    "signature": "2m727FimDuFt4mDrm1x861cDBY5svuBou7iRMExM2ve4xpEb4qzGdbr4dw47DzrWG1v6A1VJDgi2bEmuCBwhG8sd"
  },
  {
    "timestamp": 1730155115,
    "date": "2024-10-28 15:38:35",
    "token_amount": 5660643.5373,
    "sol_amount": 0.175542039,
    "price_in_sol": 3.101096860158936e-08,
    "price_in_usd": 5.488941442481317e-06,
    "market_cap": 5488.941442481317,
    "signature": "2a9uts4dcz3kVEuhKfpeZzndAPCaRxr6fhZpPjdVxfkSRc7c5XsxArtKyDTgjsX5RNf7J9ndtphTArzbW3kw8jyP"
  },
  {
    "timestamp": 1730155115,
    "date": "2024-10-28 15:38:35",
    "token_amount": 4452110.207,
    "sol_amount": 0.150083784,
    "price_in_sol": 3.371070728752964e-08,
    "price_in_usd": 5.966795189892746e-06,
    "market_cap": 5966.795189892746,
    "signature": "4Ar5S2iS76vdvWzfegv48HSPqtbXCqTKCLGBcR2Q7gQqpzJMbks7Qh1nWPjoCobMgsijqBhXPoSdA6bk8oQ7mtdG"
  },
  {
    "timestamp": 1730155115,
    "date": "2024-10-28 15:38:35",
    "token_amount": 3191681.19,
    "sol_amount": 0.108440147,
    "price_in_sol": 3.397587056619524e-08,
    "price_in_usd": 6.0137290902165575e-06,
    "market_cap": 6013.729090216558,
    "signature": "27A4agRwqDFzYCJ1NaFdAqGGzGJ6Hs7Tpwfzh2yV39xeVM1XSdP19g9Uf7244GYoit9WRVm1Y1eSxBo2Zsp6SHWT"
  },
  {
    "timestamp": 1730155113,
    "date": "2024-10-28 15:38:33",
    "token_amount": 848798.544958,
    "sol_amount": 0.029688965,
    "price_in_sol": 3.4977634182288875e-08,
    "price_in_usd": 6.191041250265131e-06,
    "market_cap": 6191.041250265131,
    "signature": "2Tbt1CLfb8AfVx9oX6ZqmnWq8tkKjYaiubY1WRgNmS7T3bijUj24azspKRVWRGgZLfANZL3kGhtAP6CVsJCuyGSY"
  },
  {
    "timestamp": 1730155113,
    "date": "2024-10-28 15:38:33",
    "token_amount": 5021279.004725,
    "sol_amount": 0.173405763,
    "price_in_sol": 3.45341819956282e-08,
    "price_in_usd": 6.112550213226191e-06,
    "market_cap": 6112.550213226191,
    "signature": "5twEZyvVmsK5BufhwXxRw147EF24gi9VXYjjbRPbcGbL4f3g6iGFMiLbvxQmzW2LzuRisdX37qCSMyCtXA4GACEC"
  },
  {
    "timestamp": 1730155113,
    "date": "2024-10-28 15:38:33",
    "token_amount": 1470030.045975,
    "sol_amount": 0.051673756,
    "price_in_sol": 3.515149648912604e-08,
    "price_in_usd": 6.2218148785753084e-06,
    "market_cap": 6221.814878575308,
    "signature": "5wEwRxZMYByvpBB3UsqunF5swwyHCSw5hf1gzw6ZdEVPFxzW1utnFgcu9fWYNaapRMV7BHDDGxuw4xfgTDS2Vt4e"
  },
  {
    "timestamp": 1730155113,
    "date": "2024-10-28 15:38:33",
    "token_amount": 1225970.423979,
    "sol_amount": 0.043007897,
    "price_in_sol": 3.5080697020743705e-08,
    "price_in_usd": 6.2092833726716355e-06,
    "market_cap": 6209.283372671635,
    "signature": "19ujsDLnH3PS9nSzxFoc4m8Av9aMJsiwbVMRmL9KT9cwp4bM9QFBAaf4e4rnzCnUKCE2ZvVqiJjySvBFD1df7P1"
  },
  {
    "timestamp": 1730155112,
    "date": "2024-10-28 15:38:32",
    "token_amount": 472901.394115,
    "sol_amount": 0.016659496,
    "price_in_sol": 3.5228265780812545e-08,
    "price_in_usd": 6.2354030432038205e-06,
    "market_cap": 6235.403043203821,
    "signature": "5Ut1fbgRucCVnH91i4EQmGEibGti6VZJRsPYmgJHYqa5qjVvR5PQwLb6cgcCfXmQBjnnJ1ivUqX9xGvGJ4N5AeHg"
  },
  {
    "timestamp": 1730155112,
    "date": "2024-10-28 15:38:32",
    "token_amount": 867591.628658,
    "sol_amount": 0.030431208,
    "price_in_sol": 3.507549749767793e-08,
    "price_in_usd": 6.208363057088994e-06,
    "market_cap": 6208.3630570889945,
    "signature": "5KQQzPCaGXQNdCBj59bgzJpgvwjaqUwr2fX8ykF5V6nVrxjgWLXNqrjcKbBwtdGKRs4mZcdwafKhA7rdg4eGUres"
  },
  {
    "timestamp": 1730155111,
    "date": "2024-10-28 15:38:31",
    "token_amount": 1380860.104883,
    "sol_amount": 0.047604156,
    "price_in_sol": 3.447427862653291e-08,
    "price_in_usd": 6.101947316896325e-06,
    "market_cap": 6101.947316896325,
    "signature": "rh3asmjYpGDGs3yiQU8ba5hPjSEtkkrZ31x3L1rhpo5CEvZCmA2AQDqyCg4XEQ9bo3prnxSo1v24ogG5efgDy94"
  },
  {
    "timestamp": 1730155111,
    "date": "2024-10-28 15:38:31",
    "token_amount": 585827.913013,
    "sol_amount": 0.020565658,
    "price_in_sol": 3.510528867466858e-08,
    "price_in_usd": 6.213636095416339e-06,
    "market_cap": 6213.636095416339,
    "signature": "2232E565vP38sZUDrRXmqnjdoUnFUxhcivTHtB3NZpdpy8Ph9VqAzcbikGsgxqhQUrLtHTatzKxzPMkPw2gqE9Kk"
  },
  {
    "timestamp": 1730155111,
    "date": "2024-10-28 15:38:31",
    "token_amount": 817230.76323,
    "sol_amount": 0.028645004,
    "price_in_sol": 3.505130409773647e-08,
    "price_in_usd": 6.204080825299355e-06,
    "market_cap": 6204.080825299355,
    "signature": "5cdbRno5oaaLscvTamn8JJN2MQmo8zsVGeSjw44FxVp5MCshsVvNRjK7Tx2MFTXWs3oJBeMdFL63pY15TShhwxK8"
  },
  {
    "timestamp": 1730155111,
    "date": "2024-10-28 15:38:31",
    "token_amount": 607340.485922,
    "sol_amount": 0.021374934,
    "price_in_sol": 3.519431767758877e-08,
    "price_in_usd": 6.2293942289332125e-06,
    "market_cap": 6229.394228933213,
    "signature": "3X6xKhtWVUb52CBg62eEnmfHR9vnbGPeE8QzoFwFKTRJKQT19Y6PqQEiKtJLA9zzmnczFyiGHkRDMKeAeHiEqY6R"
  },
  {
    "timestamp": 1730155110,
    "date": "2024-10-28 15:38:30",
    "token_amount": 1024295.899947,
    "sol_amount": 0.035673932,
    "price_in_sol": 3.482776022226182e-08,
    "price_in_usd": 6.164513559340342e-06,
    "market_cap": 6164.513559340342,
    "signature": "5KHf9qr3dxPKAMeKJQHPWjVgg6Grc3iMzbyyidfkdGY5LLLmVc84XmEUJU2AU5wyddWycYDEueYRPmkJQ4DjJe4X"
  },
  {
    "timestamp": 1730155110,
    "date": "2024-10-28 15:38:30",
    "token_amount": 1224042.44035,
    "sol_amount": 0.04249136,
    "price_in_sol": 3.471395974460666e-08,
    "price_in_usd": 6.144370874795378e-06,
    "market_cap": 6144.370874795379,
    "signature": "4Htqesmd71E9SYADazou4tFgreKvqQwoDKEPHREyXPBdgamGia3vogDnsW1P9ik1CWooJ7zr42FuQRK4hQPehx21"
  },
  {
    "timestamp": 1730155110,
    "date": "2024-10-28 15:38:30",
    "token_amount": 1508020.689639,
    "sol_amount": 0.052152045,
    "price_in_sol": 3.4583109740015904e-08,
    "price_in_usd": 6.121210423982815e-06,
    "market_cap": 6121.210423982815,
    "signature": "dANvJPdrnckKPxUaxFrtRAY17VPNDhQ8uAHceu3X7rVjtMkxGGWU6hDZAhb5hHpYFncEAwYjXrcn8reXC7rMfgj"
  },
  {
    "timestamp": 1730155110,
    "date": "2024-10-28 15:38:30",
    "token_amount": 916673.578776,
    "sol_amount": 0.032009514,
    "price_in_sol": 3.491920651050193e-08,
    "price_in_usd": 6.180699552358841e-06,
    "market_cap": 6180.699552358841,
    "signature": "2GsCUEYETnrRozUSyDJLedr9pDvnw5pMNiVaX2TqhREdvZNLX7UgNxh9Cyh8x3NhVZJsVBfRZntRxQZ9LVGrUyEB"
  },
  {
    "timestamp": 1730155109,
    "date": "2024-10-28 15:38:29",
    "token_amount": 26511053.3159,
    "sol_amount": 17.572947899,
    "price_in_sol": 6.628536289978575e-07,
    "price_in_usd": 0.00011732509233262078,
    "market_cap": 117325.09233262077,
    "signature": "3A2nwgfMCX6EZ9LCG3A5MYqG8iuAVtsjgnvpkDQynqZATQf8uWCswxXUgHsqJH3E8iwnjgZ9xXjmYo8V1UCb76xu"
  },
  {
    "timestamp": 1730155109,
    "date": "2024-10-28 15:38:29",
    "token_amount": 22412464.2562,
    "sol_amount": 2.301825918,
    "price_in_sol": 1.0270293760148404e-07,
    "price_in_usd": 1.8178419955462676e-05,
    "market_cap": 18178.419955462676,
    "signature": "3EyNarX3DTBSK8aukJbJsHf5dmCUAV1P8i5spFQUbhQkUPBDA3smygSG5DA6PD2d5Ku6jUjkJETDNZ2aoRTZqgHd"
  },
  {
    "timestamp": 1730155109,
    "date": "2024-10-28 15:38:29",
    "token_amount": 40762011.1731,
    "sol_amount": 8.816432313,
    "price_in_sol": 2.1629041500332573e-07,
    "price_in_usd": 3.828340345558865e-05,
    "market_cap": 38283.403455588654,
    "signature": "67PEREcefN1BF3KMnCN6KMr4qodoVxo5bFM85i3Ei6WhKn8FcWWXJhNgtrQh56j4kPRoArBSqNfHoFvTTo6diLzb"
  },
  {
    "timestamp": 1730155109,
    "date": "2024-10-28 15:38:29",
    "token_amount": 29571026.7229,
    "sol_amount": 4.704826766,
    "price_in_sol": 1.5910258409649846e-07,
    "price_in_usd": 2.8161157385080226e-05,
    "market_cap": 28161.157385080227,
    "signature": "iqe3W3WNmiVjfTp42aVsXniJ47SgBbSAA4BwxuwDqnxt5THUXubRkfJx6v154TzZ8mcE2dkXUrUW1pMZ4tnVTob"
  },
  {
    "timestamp": 1730155107,
    "date": "2024-10-28 15:38:27",
    "token_amount": 1540148.879863,
    "sol_amount": 0.213252986,
    "price_in_sol": 1.3846257903259936e-07,
    "price_in_usd": 2.4507876488770087e-05,
    "market_cap": 24507.876488770085,
    "signature": "2oWFtwCik9Ba7phr8gqckm8eZMqU8ugC1JzaJYFL58f4jR8kFSGMWVD8S49cVWtRoCVgWzNinDT1Dui5FELkb6FE"
  },
  {
    "timestamp": 1730155099,
    "date": "2024-10-28 15:38:19",
    "token_amount": 1375250.924736,
    "sol_amount": 0.189302857,
    "price_in_sol": 1.3764968530113116e-07,
    "price_in_usd": 2.4363994298300216e-05,
    "market_cap": 24363.994298300215,
    "signature": "4SLJZJUghMpKdQqQaLqoAQ737VGZ3K3UdMAwnNrfCRTYRnzkrBrBTdUv2fEeLttUHSRxwdLY4umEc7tFtVZ7ekL9"
  },
  {
    "timestamp": 1730155097,
    "date": "2024-10-28 15:38:17",
    "token_amount": 512598.190188,
    "sol_amount": 0.070417121,
    "price_in_sol": 1.373729411221173e-07,
    "price_in_usd": 2.431501057861476e-05,
    "market_cap": 24315.01057861476,
    "signature": "62DesnmeJ7MaeVGYzq5YVCXJCfJWbNh87NzTFFkT8p1zsqhXvdZb6Uxr8PvmLhLoP1iFu85mENTCvz54LTdsJY2f"
  },
  {
    "timestamp": 1730155094,
    "date": "2024-10-28 15:38:14",
    "token_amount": 1277098.868381,
    "sol_amount": 0.174488604,
    "price_in_sol": 1.3662889250007886e-07,
    "price_in_usd": 2.4183313972513958e-05,
    "market_cap": 24183.31397251396,
    "signature": "67fRCXWzbNTtXMHv8isV7m7SizwZgKJ4wUXpbCS6qLwtTNHegTenV68MkMLtGpbpTwEge3uxBGzwFmbw9LpWeBXb"
  },
  {
    "timestamp": 1730155094,
    "date": "2024-10-28 15:38:14",
    "token_amount": 1421272.492703,
    "sol_amount": 0.19309335,
    "price_in_sol": 1.3585948577163538e-07,
    "price_in_usd": 2.404712898157946e-05,
    "market_cap": 24047.128981579463,
    "signature": "61GCReWKvteCzsyFhMbFKECaUtwiLQsqWbienDvnNCXmFVaid869LAJqHSywWBMxFhWvixEqNvXGXLLzfJyHxVdX"
  },
  {
    "timestamp": 1730155094,
    "date": "2024-10-28 15:38:14",
    "token_amount": 882622.651255,
    "sol_amount": 0.119431874,
    "price_in_sol": 1.353147620109001e-07,
    "price_in_usd": 2.3950712875929317e-05,
    "market_cap": 23950.71287592932,
    "signature": "2QVU1veMGfcQ6KoaoGxeQkwvJjcWoUGVvtmMxFoLnSVBoTv78EWLApqsadfRSNvywrLTkLx5KNUt6oPVBYtJ3Urc"
  },
  {
    "timestamp": 1730155094,
    "date": "2024-10-28 15:38:14",
    "token_amount": 1570542.488654,
    "sol_amount": 0.211294686,
    "price_in_sol": 1.3453611572208124e-07,
    "price_in_usd": 2.381289248280838e-05,
    "market_cap": 23812.89248280838,
    "signature": "3xM8MVBLmMDf2Rt71CPbw9BmQkDfNbGg612tSGQ4LYei14bXeSbxMda4kG3ug24UdVRVHUvDKYBh4Dd2hSeA77L2"
  },
  {
    "timestamp": 1730155092,
    "date": "2024-10-28 15:38:12",
    "token_amount": 1322786.336095,
    "sol_amount": 0.176582678,
    "price_in_sol": 1.3349297099733435e-07,
    "price_in_usd": 2.362825586652818e-05,
    "market_cap": 23628.25586652818,
    "signature": "2XJSdpL1eJfHhiLss7ce2LP16TGgrAyPy8SUUoN8RWMLxaV2icHXgnHVVVd9Kr3PixW6RVrMkwmGuMzKmfaHK2cC"
  },
  {
    "timestamp": 1730155092,
    "date": "2024-10-28 15:38:12",
    "token_amount": 521920.23313,
    "sol_amount": 0.07005902,
    "price_in_sol": 1.3423319417959732e-07,
    "price_in_usd": 2.3759275369788726e-05,
    "market_cap": 23759.275369788727,
    "signature": "QSqpm6uovGJwU3iDzxBFsjH7nX1DdNBNqbAwocBPf4cC1bwffQTkmvGuMHH9NYCt7AfUiQxBnA65uZJ7HsxuSb7"
  },
  {
    "timestamp": 1730155091,
    "date": "2024-10-28 15:38:11",
    "token_amount": 1322786.336095,
    "sol_amount": 0.175639531,
    "price_in_sol": 1.327799707385138e-07,
    "price_in_usd": 2.3502054820716945e-05,
    "market_cap": 23502.054820716945,
    "signature": "L5PsVvYvGgw2ErE4HRqAFW7i1upbQ4FKTD2pUB6CYLQcbcHxf9cBBpLkfQBW1y23nPfUwSMuUB7gsfw1G76oVEY"
  },
  {
    "timestamp": 1730155091,
    "date": "2024-10-28 15:38:11",
    "token_amount": 1063523.694369,
    "sol_amount": 0.142619457,
    "price_in_sol": 1.3410087406150143e-07,
    "price_in_usd": 2.3735854708885755e-05,
    "market_cap": 23735.854708885756,
    "signature": "4YkFaBdNQas6YAmQ8mmD9RkhCavHxXEfDx1y5UsLXAbyi62WpCF1dZRNgPG1Lk2rovHZDQxTx7TozEv4ZjSPKGom"
  },
  {
    "timestamp": 1730155091,
    "date": "2024-10-28 15:38:11",
    "token_amount": 924145.943486,
    "sol_amount": 0.121697353,
    "price_in_sol": 1.3168629247123196e-07,
    "price_in_usd": 2.3308473767408057e-05,
    "market_cap": 23308.473767408057,
    "signature": "ZLUzuxByEZyo9smCQmxJz9nWgiSvNf7SUz1Mk16grfCQbcSrponasS4zaH5PoAiozEZmYzXqfUZKzkoqxoHGNw8"
  },
  {
    "timestamp": 1730155091,
    "date": "2024-10-28 15:38:11",
    "token_amount": 1038410.387482,
    "sol_amount": 0.136179237,
    "price_in_sol": 1.3114202115236502e-07,
    "price_in_usd": 2.321213774396861e-05,
    "market_cap": 23212.13774396861,
    "signature": "4zMNh5DYhwxKbCWEPHR7jKxwL5TJQK3BrT2rFeVBNd6PdQTLcf5BvhgQWf4qe7WK4iHb3dueoTxhkTsbjxnRwsrM"
  },
  {
    "timestamp": 1730155090,
    "date": "2024-10-28 15:38:10",
    "token_amount": 977400.597982,
    "sol_amount": 0.127674378,
    "price_in_sol": 1.3062645783479587e-07,
    "price_in_usd": 2.312088303675887e-05,
    "market_cap": 23120.88303675887,
    "signature": "5iXvWqiC1Drnnu7U2zy3oRb7oNLYZijXvGXcmNKZoVE2dJdYDV5Pewmve33rgbNa1n7fRngNeM1d8HAb4sQ6vvf2"
  },
  {
    "timestamp": 1730155089,
    "date": "2024-10-28 15:38:09",
    "token_amount": 1159396.322383,
    "sol_amount": 0.150765978,
    "price_in_sol": 1.3003834417045468e-07,
    "price_in_usd": 2.301678691817048e-05,
    "market_cap": 23016.786918170477,
    "signature": "2afJGmH8SUWWww27ZJoNugBQMeXVKfECVPJ5Q3iVG5AyPcWRgkt2e7UeHMH5rH3aeaxAT7Y1rQ12JnDjof1eZyL7"
  },
  {
    "timestamp": 1730155088,
    "date": "2024-10-28 15:38:08",
    "token_amount": 2530562.821004,
    "sol_amount": 0.326251157,
    "price_in_sol": 1.28924346114656e-07,
    "price_in_usd": 2.2819609262294112e-05,
    "market_cap": 22819.60926229411,
    "signature": "62N2YJbXVt3uxQiVBmph7yvEtpTBP3u3jEhuzkqr36McdNRoaHUQLL59AzGem1Q7FSPLmJrdshvFj647ahErkiJ3"
  },
  {
    "timestamp": 1730155087,
    "date": "2024-10-28 15:38:07",
    "token_amount": 7875285.709538,
    "sol_amount": 1.026909379,
    "price_in_sol": 1.3039646012541215e-07,
    "price_in_usd": 2.308017344219795e-05,
    "market_cap": 23080.17344219795,
    "signature": "gk97unp2prSrg7j5DjqkjJDTcfhW5k6Wc8ciJEDCGZ563GrBFZkzNxYD7Fp9zn2eW4u1PGQeB2ut1ZUfYXfKFe2"
  },
  {
    "timestamp": 1730155085,
    "date": "2024-10-28 15:38:05",
    "token_amount": 1152558.289727,
    "sol_amount": 0.14606108,
    "price_in_sol": 1.2672771633493406e-07,
    "price_in_usd": 2.2430805791283328e-05,
    "market_cap": 22430.80579128333,
    "signature": "32THPr1rjppbStNvsmKuS44ghSkPkyE6sZjqDqD1MPyEtVZR2qkpoHUzMtGCSn5PAQAPs2Zy3b88jjUXrp7RXYRF"
  },
  {
    "timestamp": 1730155084,
    "date": "2024-10-28 15:38:04",
    "token_amount": 566682.425084,
    "sol_amount": 0.071677921,
    "price_in_sol": 1.2648693135202684e-07,
    "price_in_usd": 2.238818684930875e-05,
    "market_cap": 22388.18684930875,
    "signature": "34DBW8kcUAVvNbTwg94tvPCqPFwhsT1CMN4JoYfqJpoiYjnv2cSRqP7tSo6XTHB7WTcADdo81aBybr4u1a1xmTfs"
  },
  {
    "timestamp": 1730155079,
    "date": "2024-10-28 15:37:59",
    "token_amount": 1102306.974282,
    "sol_amount": 0.138771938,
    "price_in_sol": 1.2589227977115055e-07,
    "price_in_usd": 2.2282933519493648e-05,
    "market_cap": 22282.933519493647,
    "signature": "59EAkxZq6LsMZgrLFviAn2vamZeB2uNDkB28oAfouG67B5fiitKBAVVodCycEKVYHUMBGp4YsyqQBmkG5oRyfuWz"
  },
  {
    "timestamp": 1730155077,
    "date": "2024-10-28 15:37:57",
    "token_amount": 595464.599644,
    "sol_amount": 0.07481318,
    "price_in_sol": 1.2563833357134457e-07,
    "price_in_usd": 2.223798504212799e-05,
    "market_cap": 22237.985042127988,
    "signature": "3wu6RtsSRheiKJGE9PQGjRz6K4wobCrn8SVn4zCHfeSkFKvj5Mfb4H5n7qgFi3oUFyXpWo4e6woWDSkmhEUHc4cK"
  },
  {
    "timestamp": 1730155077,
    "date": "2024-10-28 15:37:57",
    "token_amount": 1053359.709611,
    "sol_amount": 0.130780097,
    "price_in_sol": 1.241552109946339e-07,
    "price_in_usd": 2.19754723460502e-05,
    "market_cap": 21975.472346050203,
    "signature": "QiJPZ5V2RTXVLPvw8m5hQqxJHEsXcWhrWd3mYXn4j2E8qpvrFkdJ4hdufs7NFEjgx7bA7W5bZbu5uYgr57Kn7Wu"
  },
  {
    "timestamp": 1730155076,
    "date": "2024-10-28 15:37:56",
    "token_amount": 822794.43668,
    "sol_amount": 0.103431451,
    "price_in_sol": 1.2570752351869195e-07,
    "price_in_usd": 2.2250231662808476e-05,
    "market_cap": 22250.231662808477,
    "signature": "2wVSjUnf54yfqVtppLUH2TVipiSsj1NyTvjAaXLoB9jt3GTdGcBowcFQTY8T4FsH5FpP4pMD6aWqepiZznWDvufn"
  },
  {
    "timestamp": 1730155076,
    "date": "2024-10-28 15:37:56",
    "token_amount": 866488.711461,
    "sol_amount": 0.108555239,
    "price_in_sol": 1.2528176947275323e-07,
    "price_in_usd": 2.2174873196677323e-05,
    "market_cap": 22174.873196677323,
    "signature": "2rnKRjwhXFa4LTEnfNf9WWzTAzSH9Wk4FStKpcBHgDCahwVhz1PN35ypNXCQdB7M5di7upZDNacNbm6ghr2cAUtw"
  },
  {
    "timestamp": 1730155075,
    "date": "2024-10-28 15:37:55",
    "token_amount": 1390259.03976,
    "sol_amount": 0.173279964,
    "price_in_sol": 1.2463861700903831e-07,
    "price_in_usd": 2.206103521059978e-05,
    "market_cap": 22061.03521059978,
    "signature": "3qctDEcGXcBdQ9xCwG2qomizbGqfpJmHPdvdtr9xsRdGkzABgn1TZrMbNqhqesTphAqDmZZ8c6mYr5ffb6eooLgH"
  },
  {
    "timestamp": 1730155074,
    "date": "2024-10-28 15:37:54",
    "token_amount": 1149966.684031,
    "sol_amount": 0.142657709,
    "price_in_sol": 1.2405377562760275e-07,
    "price_in_usd": 2.1957518286085687e-05,
    "market_cap": 21957.518286085688,
    "signature": "wtX76yPUtR385kgch5A9mj7izdYo5rFThsG9ZECGwuumGiAifNoDpM6xXgM8WXs1qJZxJR7GWhbK3ZGUpeQTC83"
  },
  {
    "timestamp": 1730155074,
    "date": "2024-10-28 15:37:54",
    "token_amount": 658986.625888,
    "sol_amount": 0.08359161,
    "price_in_sol": 1.2684872001363963e-07,
    "price_in_usd": 2.2452223442414214e-05,
    "market_cap": 22452.223442414215,
    "signature": "VTy6YQinhQTRZZXubWw1maQdjBy6VW4BzRVeLskzw1p6L5S2ek4L46ZwFArTpVtTeSU5A3Pgua85yEjxx8pCUqN"
  },
  {
    "timestamp": 1730155074,
    "date": "2024-10-28 15:37:54",
    "token_amount": 1128641.071383,
    "sol_amount": 0.13903977,
    "price_in_sol": 1.2319219415755022e-07,
    "price_in_usd": 2.180501836588639e-05,
    "market_cap": 21805.01836588639,
    "signature": "2nMLrp9B7nvXpcxSFH2rkTwsX3XagHp9vNcCMovZKwvtxsS2jLoY8mxi6Mf6Yvi2FbPngRNcmE45JQrP1UcnN7se"
  },
  {
    "timestamp": 1730155073,
    "date": "2024-10-28 15:37:53",
    "token_amount": 1739847.175529,
    "sol_amount": 0.211943941,
    "price_in_sol": 1.218175618991125e-07,
    "price_in_usd": 2.1561708456142915e-05,
    "market_cap": 21561.708456142915,
    "signature": "4MA48yhCyYDWoEXLqYiif2crgM7oyzVdnigHUh7DkjbBVqiyNjyvp4bmajzNipfKx7dgXSK1G26nEX8g24mof1R2"
  },
  {
    "timestamp": 1730155073,
    "date": "2024-10-28 15:37:53",
    "token_amount": 1491990.181844,
    "sol_amount": 0.180648527,
    "price_in_sol": 1.2107889797018002e-07,
    "price_in_usd": 2.1430964940721862e-05,
    "market_cap": 21430.964940721864,
    "signature": "2cVLhYEmhzctPTuXjvbP6CbrWY5t696HRn9VLSdCekkaRSx6s9r5zcsp85z8qX5c7Ny7Xqepp3KWv1XTFHALaCM4"
  },
  {
    "timestamp": 1730155073,
    "date": "2024-10-28 15:37:53",
    "token_amount": 1323670.349975,
    "sol_amount": 0.162253592,
    "price_in_sol": 1.225785498655798e-07,
    "price_in_usd": 2.1696403326207624e-05,
    "market_cap": 21696.403326207623,
    "signature": "XVJwHuVBXy4BRg1Uwd5kabUTihpf9PPmE6cLkLDzwb3CLArcJt9rXTxP2XQ6RRXhJWcwbqrssP4M9RWiYJSGdKW"
  },
  {
    "timestamp": 1730155073,
    "date": "2024-10-28 15:37:53",
    "token_amount": 1119772.719869,
    "sol_amount": 0.13495527,
    "price_in_sol": 1.2052023379868385e-07,
    "price_in_usd": 2.133208138236704e-05,
    "market_cap": 21332.08138236704,
    "signature": "2q4f8gWx3La9BcoPBbd3fdfwKhSz3NpcRyxkyAqm5ptG482VXbz7npwxojzCG5kH8Q3ty57LKihHNKMZRxsBBPD5"
  },
  {
    "timestamp": 1730155073,
    "date": "2024-10-28 15:37:53",
    "token_amount": 696258.124861,
    "sol_amount": 0.083698986,
    "price_in_sol": 1.202125806671334e-07,
    "price_in_usd": 2.127762677808261e-05,
    "market_cap": 21277.62677808261,
    "signature": "49qELUaMCiQopmvMXkAqXyaBbPtyPb6dWVptZgVJrESr8HF7CEMngPhuK5FpoALX2jisdUU5d2kCLJgQ3HsdyEXk"
  },
  {
    "timestamp": 1730155073,
    "date": "2024-10-28 15:37:53",
    "token_amount": 1464617.255407,
    "sol_amount": 0.17510847,
    "price_in_sol": 1.1955920180070486e-07,
    "price_in_usd": 2.116197871872476e-05,
    "market_cap": 21161.97871872476,
    "signature": "5vD8Xg8f7RhSz7PgVcSDj1GsAUpyL8TS9JfB5U9AWREavnYPwmfPiTbKden2hxgTMQXQ6G1smDrcEwreLjvhQ5wA"
  },
  {
    "timestamp": 1730155073,
    "date": "2024-10-28 15:37:53",
    "token_amount": 1162484.439658,
    "sol_amount": 0.138332417,
    "price_in_sol": 1.1899722033328642e-07,
    "price_in_usd": 2.1062507998991694e-05,
    "market_cap": 21062.507998991696,
    "signature": "5MPm3oAnC44yCePZuU86Ji3Fx38VbEUrSQ2JcebLWBmogdbqFQ5QA6Uw9mytiTsZ4xSd5X7bjxxKk3uSqqCxgjHN"
  },
  {
    "timestamp": 1730155073,
    "date": "2024-10-28 15:37:53",
    "token_amount": 1119895.395039,
    "sol_amount": 0.1326954,
    "price_in_sol": 1.1848910227493069e-07,
    "price_in_usd": 2.097257110266273e-05,
    "market_cap": 20972.571102662732,
    "signature": "FugpoquLB7Yec65k8pKVTQ9tH29ZXd98KUvqMBfX9hicFqgCbiaFkDtDkuvnhQNttPfDmRps9US4Zh8AJ96m6Qk"
  },
  {
    "timestamp": 1730155071,
    "date": "2024-10-28 15:37:51",
    "token_amount": 697350.113817,
    "sol_amount": 0.08242071,
    "price_in_sol": 1.1819129066870563e-07,
    "price_in_usd": 2.0919858448360896e-05,
    "market_cap": 20919.858448360897,
    "signature": "1k69PkyFGCwMNP3CXqtjwaz86weQSopUUJDb2FG4UX1FzhScJ2KHD76FGHqYCeKKAZouv3XavoKfV6e4Gd8MRdi"
  },
  {
    "timestamp": 1730155071,
    "date": "2024-10-28 15:37:51",
    "token_amount": 1476276.018157,
    "sol_amount": 0.175572924,
    "price_in_sol": 1.1892960519617954e-07,
    "price_in_usd": 2.1050540119723778e-05,
    "market_cap": 21050.540119723777,
    "signature": "42A8uiRg1cfdXiPcDW6PYtxfNNhBnQEdnWSCZAWGgb9jUqBzLhH2HDEbNCcoDpPAWBqDEq7Ke6iqG1bzUEXKq7AD"
  },
  {
    "timestamp": 1730155068,
    "date": "2024-10-28 15:37:48",
    "token_amount": 1766618.253303,
    "sol_amount": 0.208388538,
    "price_in_sol": 1.1795900875040853e-07,
    "price_in_usd": 2.087874454882231e-05,
    "market_cap": 20878.74454882231,
    "signature": "5GZczmXTq2aVqBwKC16seyQXQ5kv86aZuoVytVxfe5sow33Ce3mJHu8Gy7DZqndvkLEGsM1eZfM8VHRSCbJLeyMB"
  },
  {
    "timestamp": 1730155068,
    "date": "2024-10-28 15:37:48",
    "token_amount": 715531.86651,
    "sol_amount": 0.085352864,
    "price_in_sol": 1.192859018513149e-07,
    "price_in_usd": 2.1113604627682735e-05,
    "market_cap": 21113.604627682736,
    "signature": "32sHhLf6X6Mq5burqhceT3vFTGhPkZTpPXiTAKRKkfsWxh34i5Fr9MK7XPEPEgDWafu6neKTWd53m3qaxwj4dsku"
  },
  {
    "timestamp": 1730155068,
    "date": "2024-10-28 15:37:48",
    "token_amount": 583863.067229,
    "sol_amount": 0.069892848,
    "price_in_sol": 1.197076025577534e-07,
    "price_in_usd": 2.118824565272235e-05,
    "market_cap": 21188.24565272235,
    "signature": "2tULpYmRokdYmsN93gx5Cfeuyx81vTcWyZxujEM8kX378xRZamcooLa5vSKW49WU9bin6rXHRMAdMnx82bAVnG7m"
  },
  {
    "timestamp": 1730155065,
    "date": "2024-10-28 15:37:45",
    "token_amount": 940717.793188,
    "sol_amount": 0.108880942,
    "price_in_sol": 1.1574240732814588e-07,
    "price_in_usd": 2.048640609708182e-05,
    "market_cap": 20486.40609708182,
    "signature": "4fAAnjcNPrHBebycPfiBQtSxXTU2hV5MRoyyFDHTTNvJ2wdN2hpooCwrQaZ46k1W1cR8ccLDRpG8KKY3QNFBVJvU"
  },
  {
    "timestamp": 1730155065,
    "date": "2024-10-28 15:37:45",
    "token_amount": 245016.968861,
    "sol_amount": 0.033537427,
    "price_in_sol": 1.3687797688422977e-07,
    "price_in_usd": 2.422740190850867e-05,
    "market_cap": 24227.401908508673,
    "signature": "5CgnK3iodHzRGVSjJ4AqDK87G1PEJKp7fiFyujnq8WNWByQjyFpZ6Cr9LuMWsM8ZR44N1NBXiV6uKQdiHnZbsWbJ"
  },
  {
    "timestamp": 1730155057,
    "date": "2024-10-28 15:37:37",
    "token_amount": 928477.681043,
    "sol_amount": 0.14172621,
    "price_in_sol": 1.5264363688397193e-07,
    "price_in_usd": 2.701792372846303e-05,
    "market_cap": 27017.92372846303,
    "signature": "mciKuJTJ1KcG5qFhcEsatG6rAopuXkinEMr17oJYL9YcoKgQRfSnXi7LrQkYH7ufurZg46B9ToMxUqRtV8cSn8j"
  },
  {
    "timestamp": 1730155056,
    "date": "2024-10-28 15:37:36",
    "token_amount": 1652334.790171,
    "sol_amount": 0.189321204,
    "price_in_sol": 1.145779929867646e-07,
    "price_in_usd": 2.0280304758657335e-05,
    "market_cap": 20280.304758657334,
    "signature": "2Y16kyeMFMvb9JN7ZcYVZYEwjNHm94kBch9esqMe12zrDShAKYFW7j4QSZE2PqTvcGZwCrTFFqpZ7sWx1waZye9g"
  },
  {
    "timestamp": 1730155056,
    "date": "2024-10-28 15:37:36",
    "token_amount": 1614019.7645,
    "sol_amount": 0.183811059,
    "price_in_sol": 1.1388401991281811e-07,
    "price_in_usd": 2.0157471524568804e-05,
    "market_cap": 20157.471524568806,
    "signature": "JoegVaWLdaF1Z8u2YVH6ptb7X7aATxrR2X4R3dFsd8eFkjjTHnAVJ6F8MxVMUKfPwWw4rwAzSavLFRGVTgXNnWL"
  },
  {
    "timestamp": 1730155056,
    "date": "2024-10-28 15:37:36",
    "token_amount": 1805542.033928,
    "sol_amount": 0.205332773,
    "price_in_sol": 1.1372361824958106e-07,
    "price_in_usd": 2.012908043017585e-05,
    "market_cap": 20129.080430175847,
    "signature": "MsLmnJkTG7gapwkcEgXBrEaq9Xv6NFjv5iYW7C3d287ZihG6GZtZdkX3uBZzSmtNV4q97eJzwMo72fyBs3DUY5G"
  },
  {
    "timestamp": 1730155056,
    "date": "2024-10-28 15:37:36",
    "token_amount": 1316898.932978,
    "sol_amount": 0.149192574,
    "price_in_sol": 1.1329083065062549e-07,
    "price_in_usd": 2.0052477025160712e-05,
    "market_cap": 20052.47702516071,
    "signature": "5kwCTMhu5Y5rjPE5choHjjMQRCwF5LfZ3rd8J5gHCGm31jG4SGKcN7ss2NCZbuFqrFuEg1Cb5kfeq64guvaM4ssU"
  },
  {
    "timestamp": 1730155055,
    "date": "2024-10-28 15:37:35",
    "token_amount": 1077053.657986,
    "sol_amount": 0.120706764,
    "price_in_sol": 1.1207126321423161e-07,
    "price_in_usd": 1.9836613588918994e-05,
    "market_cap": 19836.613588918994,
    "signature": "zG93EETGceNe1C2xSZdEViRzCGsNa4M4SvLpWYptf6so1TDnkKDYjaMqbNQBZwX7xU3UaLpch8gfZWqqAEDjJXn"
  },
  {
    "timestamp": 1730155055,
    "date": "2024-10-28 15:37:35",
    "token_amount": 721702.381983,
    "sol_amount": 0.080680929,
    "price_in_sol": 1.1179252142457314e-07,
    "price_in_usd": 1.9787276292149446e-05,
    "market_cap": 19787.276292149447,
    "signature": "5oeq9GbfKP6pg5Dwkuev9MBMNN78qTHJaxrUibdMoaqYpQWoBkHBhRy1mfdbUgsso1HyEYswVw5vZwKXfSg8DGzP"
  },
  {
    "timestamp": 1730155055,
    "date": "2024-10-28 15:37:35",
    "token_amount": 1527791.620524,
    "sol_amount": 0.171898328,
    "price_in_sol": 1.1251424977775603e-07,
    "price_in_usd": 1.991502221066282e-05,
    "market_cap": 19915.022210662817,
    "signature": "64HKFo5YE7DV4duG3HQBaEHdYR4b81AHggRsZFV921pFCW8su1GHW7CdyZJpNB3Skzc9CGHdyf46LHKTXJAB7cMZ"
  },
  {
    "timestamp": 1730155055,
    "date": "2024-10-28 15:37:35",
    "token_amount": 1527791.620524,
    "sol_amount": 0.170944389,
    "price_in_sol": 1.1188985899881407e-07,
    "price_in_usd": 1.9804505042790092e-05,
    "market_cap": 19804.505042790093,
    "signature": "61LtHWZyGyjjgqMQM11dFNztkM4JS9DFnxH6Ef4tEaDBNiPiUaSE3dFsKUQiB4k8oXXwW2CL9MsK2kaGqPhWNURr"
  },
  {
    "timestamp": 1730155054,
    "date": "2024-10-28 15:37:34",
    "token_amount": 750531.573053,
    "sol_amount": 0.082732456,
    "price_in_sol": 1.1023181298484522e-07,
    "price_in_usd": 1.9511030898317603e-05,
    "market_cap": 19511.030898317604,
    "signature": "3T9pf3t6ie1aRk73xnLisxKwukN3QQnvHLt95cwdC4LmyRwujUjs4J3URbS4PYWkEX9Bd9w2JPEYAVH2EfTwHbrD"
  },
  {
    "timestamp": 1730155053,
    "date": "2024-10-28 15:37:33",
    "token_amount": 1931607.902821,
    "sol_amount": 0.21254889,
    "price_in_sol": 1.100372853567149e-07,
    "price_in_usd": 1.9476599508138538e-05,
    "market_cap": 19476.599508138537,
    "signature": "2Ws8UqnWL5tWtB4j2AVpjnTv69CjRsn7PVn5pvRuL6qJ2yKhbwZ2xHHEY6HJhKGYpXEwjVQcqVhcasez586CxdDT"
  },
  {
    "timestamp": 1730155053,
    "date": "2024-10-28 15:37:33",
    "token_amount": 1355254.969933,
    "sol_amount": 0.150689859,
    "price_in_sol": 1.1118930558686658e-07,
    "price_in_usd": 1.9680507088875384e-05,
    "market_cap": 19680.507088875383,
    "signature": "YnEJnQaN8Zvu6yR65zmcMBLUc6xhzpP8oAYSF1wxps9wFYGBV8VVMyxig4FMiMGTgQxU4bV2Dmdbo34aCtjdex4"
  },
  {
    "timestamp": 1730155052,
    "date": "2024-10-28 15:37:32",
    "token_amount": 1030043.256149,
    "sol_amount": 0.110771996,
    "price_in_sol": 1.0754111085988836e-07,
    "price_in_usd": 1.903477662220024e-05,
    "market_cap": 19034.77662220024,
    "signature": "4Foy6apvZsNHKTMSjCQTachgAefm2H7MFM55JmnwgPehMQdPYDatjrEEj9VzbnEf2LXb4EEyuiYgrKa2S1xgwy2q"
  },
  {
    "timestamp": 1730155052,
    "date": "2024-10-28 15:37:32",
    "token_amount": 617361.976338,
    "sol_amount": 0.066674295,
    "price_in_sol": 1.0799870668338088e-07,
    "price_in_usd": 1.9115771082958415e-05,
    "market_cap": 19115.771082958414,
    "signature": "5ZWEvm6fLVhQHYVV4kZhgtZvNDopHNyJmTid3Ngzyp15GwqYxohfHTvyi6RFheknCzGH1hnrnLAR99a3AagFmFd3"
  },
  {
    "timestamp": 1730155052,
    "date": "2024-10-28 15:37:32",
    "token_amount": 777126.250354,
    "sol_amount": 0.086438957,
    "price_in_sol": 1.1122897593618146e-07,
    "price_in_usd": 1.9687528740704116e-05,
    "market_cap": 19687.528740704118,
    "signature": "48DRRLNx993PwTsLVMN8jJYLorx94APxKE2pzwxjTcRGTGxc2bHoMZN4JEV6rwopnXPEvN8XwyYX8Pq8jvdUUY5c"
  },
  {
    "timestamp": 1730155052,
    "date": "2024-10-28 15:37:32",
    "token_amount": 1012715.323742,
    "sol_amount": 0.109562294,
    "price_in_sol": 1.0818666552330372e-07,
    "price_in_usd": 1.914903979762476e-05,
    "market_cap": 19149.03979762476,
    "signature": "5dFxGN6pZG4aCX3eUQvzFBmeji9hjixmdSGph2jp7xPT4sFstpZ22fRUaHtFecWj1JEPAPc5ndDQvvufvf3q7hnA"
  },
  {
    "timestamp": 1730155050,
    "date": "2024-10-28 15:37:30",
    "token_amount": 1078663.474141,
    "sol_amount": 0.115548462,
    "price_in_sol": 1.0712188256121094e-07,
    "price_in_usd": 1.8960573213334337e-05,
    "market_cap": 18960.573213334337,
    "signature": "54gTPCDo39HKdeuoNyNdKZXBp9ozxX9d7u15bKqfJTdCC7DT2Kkij7ZerUYvYkeTikPvVDmm84yj7tJjbeYvsJ9J"
  },
  {
    "timestamp": 1730155050,
    "date": "2024-10-28 15:37:30",
    "token_amount": 1580657.423688,
    "sol_amount": 0.170455009,
    "price_in_sol": 1.0783804665421636e-07,
    "price_in_usd": 1.9087334257796296e-05,
    "market_cap": 19087.334257796298,
    "signature": "5QXz7qXZj1kQ4DqurSssa3EMP9eQpGV3VWCXCu4AyMLYo18QPyQBdh6kXQ2DQJNa9nzBgwDGmiFZN63FHPDCgXJf"
  },
  {
    "timestamp": 1730155048,
    "date": "2024-10-28 15:37:28",
    "token_amount": 1777484.855815,
    "sol_amount": 0.190256429,
    "price_in_sol": 1.0703687762941021e-07,
    "price_in_usd": 1.8945527340405608e-05,
    "market_cap": 18945.52734040561,
    "signature": "5NkUKsouBkwUhGZ2tgaiKkpS3NVYgg5sTYwsH9Zj7rCbPAiv3TcfCub1ivgfjQYF3v8zByDqZXXvKDM59zVeSW5K"
  },
  {
    "timestamp": 1730155048,
    "date": "2024-10-28 15:37:28",
    "token_amount": 1608588.559452,
    "sol_amount": 0.16931637,
    "price_in_sol": 1.0525772361434748e-07,
    "price_in_usd": 1.8630617079739503e-05,
    "market_cap": 18630.617079739503,
    "signature": "66Z1ryKQTfP6rh9PmjCKkWEkEi8qSS5PEpkNJu1jum81XUTpZfrxQv5JPS3fsX9ebfRYNrg2oXrfo1SkQAqpURWn"
  },
  {
    "timestamp": 1730155035,
    "date": "2024-10-28 15:37:15",
    "token_amount": 787521.776617,
    "sol_amount": 0.08264373,
    "price_in_sol": 1.0494151711590396e-07,
    "price_in_usd": 1.8574648529515e-05,
    "market_cap": 18574.648529515,
    "signature": "4Y4Jz5JmUHg2ygR29uL8B1Cc6K6XkuUe754qcYb6hbowHnoGfvW5qRJuwLqFB8sE3rSNhH2cyKNQKYMQE1Nb16aZ"
  },
  {
    "timestamp": 1730155035,
    "date": "2024-10-28 15:37:15",
    "token_amount": 1478779.396626,
    "sol_amount": 0.154376546,
    "price_in_sol": 1.0439457457429234e-07,
    "price_in_usd": 1.8477839699649744e-05,
    "market_cap": 18477.839699649743,
    "signature": "4ZrrjJn9B2sUxUZv1tq2ns4A5PCSHjp2NQ5FxUxeoWZTd8EKFZhX1PBTHBURknWWwL7fNhonxYA8PeF46zdaRVYA"
  },
  {
    "timestamp": 1730155035,
    "date": "2024-10-28 15:37:15",
    "token_amount": 5021279.004725,
    "sol_amount": 0.52949124,
    "price_in_sol": 1.0544947602030305e-07,
    "price_in_usd": 1.866455725559364e-05,
    "market_cap": 18664.557255593638,
    "signature": "3aHiGLA22SGx7rJuFiCGDh4wt3MBQwP6XEQYDEk1Xzhip6XcUE39AzUCcAMy49ShbTv5M8xZmniAfn8MNNPHSZYQ"
  },
  {
    "timestamp": 1730155035,
    "date": "2024-10-28 15:37:15",
    "token_amount": 2530562.821004,
    "sol_amount": 0.259298716,
    "price_in_sol": 1.0246681641245456e-07,
    "price_in_usd": 1.8136626505004458e-05,
    "market_cap": 18136.626505004457,
    "signature": "4UvFRmWMwroCboPsd1c4f5AhUD26qaeF6nFGnMWexmXbP4SkzaiJjGwCRumaRQ1SZ7FyAwF2LczHLMWdArC8EUd3"
  },
  {
    "timestamp": 1730155035,
    "date": "2024-10-28 15:37:15",
    "token_amount": 1154302.760625,
    "sol_amount": 0.119902789,
    "price_in_sol": 1.0387464458204911e-07,
    "price_in_usd": 1.838581209102269e-05,
    "market_cap": 18385.81209102269,
    "signature": "ciLbpbFNytZb8XKHTtsqjj2hh5wsEST7M2pYDPGgrXMaJdz3ypc5bQWp8AckEz1TkZgTY4R76hQdmF8ior6NoV4"
  },
  {
    "timestamp": 1730155034,
    "date": "2024-10-28 15:37:14",
    "token_amount": 1154302.760625,
    "sol_amount": 0.118382457,
    "price_in_sol": 1.0255754472587548e-07,
    "price_in_usd": 1.815268541647996e-05,
    "market_cap": 18152.68541647996,
    "signature": "2VCcNj9H8VeQdtFTwY8MthdQsXV5MmKJiXi8BAVESQ7SkBdgSv2us9QQCUQf441dKPBWMdbqbpFy6rkurs842A5Y"
  },
  {
    "timestamp": 1730155034,
    "date": "2024-10-28 15:37:14",
    "token_amount": 1326609.855895,
    "sol_amount": 0.13513941,
    "price_in_sol": 1.0186823910548132e-07,
    "price_in_usd": 1.8030678321670194e-05,
    "market_cap": 18030.678321670195,
    "signature": "7voK8kj4SPeh4oJZFAZy3czdf8K7NN2sHBjsv4zndMf7t7doxo6eudkqBor8U67zp3QSKo3UeAcsxjkb3ohfSpj"
  },
  {
    "timestamp": 1730155033,
    "date": "2024-10-28 15:37:13",
    "token_amount": 714109.965449,
    "sol_amount": 0.07352739,
    "price_in_sol": 1.0296368004578861e-07,
    "price_in_usd": 1.8224571368104583e-05,
    "market_cap": 18224.57136810458,
    "signature": "2NxYto9fVvpZoP3k1kTYVXBU39fgRXgcopnxfGYS49Qv9MXYZBCModD79suHmjdkdVRLGz7sJ18u6nzoXATZQGNC"
  },
  {
    "timestamp": 1730155033,
    "date": "2024-10-28 15:37:13",
    "token_amount": 1332286.480761,
    "sol_amount": 0.134755744,
    "price_in_sol": 1.0114622188692311e-07,
    "price_in_usd": 1.790288127398539e-05,
    "market_cap": 17902.88127398539,
    "signature": "4mum5RT3Mbbaf7CXXCEzJfpoDFN325D79ZJxjmUAHPwLmchcvtvTmt9RJg3gn6uWQoh5r1EBhkgPWAkZtMftXB3C"
  },
  {
    "timestamp": 1730155033,
    "date": "2024-10-28 15:37:13",
    "token_amount": 1374149.146258,
    "sol_amount": 0.138272596,
    "price_in_sol": 1.0062415450064906e-07,
    "price_in_usd": 1.7810475346614884e-05,
    "market_cap": 17810.475346614883,
    "signature": "4M5ELDfw7dJNHEmckhj7h5xxRXzBRpxdamYqqCtu2NuJwfm6JtdvAQTLXVyJCyVuBSr827GGTppPJj22VNaWqK6n"
  },
  {
    "timestamp": 1730155033,
    "date": "2024-10-28 15:37:13",
    "token_amount": 1802899.759788,
    "sol_amount": 0.179728106,
    "price_in_sol": 9.968835206963138e-08,
    "price_in_usd": 1.7644838316324754e-05,
    "market_cap": 17644.838316324753,
    "signature": "2U3Lf7qmvdhtz5hkw6HJFUpGXA3xGEk6pjQu9tC4UEcGhdf8uT24yTLPaeRPk4L9g15XUbzH8PCrGYiKrxfA86jj"
  },
  {
    "timestamp": 1730155032,
    "date": "2024-10-28 15:37:12",
    "token_amount": 2061009.123958,
    "sol_amount": 0.203779348,
    "price_in_sol": 9.887357878778255e-08,
    "price_in_usd": 1.7500623445437513e-05,
    "market_cap": 17500.62344543751,
    "signature": "5pGYpA1WGBNM3SkQCfrB21mwRdFHKritopfoRetd6ZFQ2BN6Zp8zLAkL4hve2pBtTmwAT5iCBVXBpue7fZfcNdHV"
  },
  {
    "timestamp": 1730155030,
    "date": "2024-10-28 15:37:10",
    "token_amount": 2040052.031428,
    "sol_amount": 0.199657068,
    "price_in_sol": 9.786861556675278e-08,
    "price_in_usd": 1.7322744955315244e-05,
    "market_cap": 17322.744955315244,
    "signature": "2fgjAqmw7EYYGkyRhfowZ9j2jhBCZs1Niphwi9m6Fb5QCMahbyD6EW53uV8XHfRTBispyqYWEo7urRVLJQPLeFYJ"
  },
  {
    "timestamp": 1730155030,
    "date": "2024-10-28 15:37:10",
    "token_amount": 969231.069698,
    "sol_amount": 0.096527061,
    "price_in_sol": 9.959138126894405e-08,
    "price_in_usd": 1.7627674484603097e-05,
    "market_cap": 17627.674484603096,
    "signature": "3Uhqnnco5LXt5iV2WsqQxgusjTKtUqvYfWiunYVtJaSvxGio2xLZ4xwgAStamUxdQpNKUXVgmfgq8GmZEXe5tkxg"
  },
  {
    "timestamp": 1730155029,
    "date": "2024-10-28 15:37:09",
    "token_amount": 1111169.373483,
    "sol_amount": 0.109190809,
    "price_in_sol": 9.826657538061683e-08,
    "price_in_usd": 1.739318384236918e-05,
    "market_cap": 17393.183842369177,
    "signature": "3i1wFupieivv2DH6REsTpLSNnzhW6JzvoFK3Ss4FrsqYgd5Qnb9aC5kVS7YsnkpeS48TkVca58nKmfNsBze8VZ2e"
  },
  {
    "timestamp": 1730155014,
    "date": "2024-10-28 15:36:54",
    "token_amount": 1053359.709611,
    "sol_amount": 0.103244137,
    "price_in_sol": 9.801413141017848e-08,
    "price_in_usd": 1.734850125960159e-05,
    "market_cap": 17348.50125960159,
    "signature": "5uAzntdgBkNsfkg29zSkG2u57s9e2JkSKwRvKPbMUwpyfKFpDrS7ZxsYpt2ykPJzp8q58JRMPZPgf1uPCEFRDuDc"
  },
  {
    "timestamp": 1730155012,
    "date": "2024-10-28 15:36:52",
    "token_amount": 1380860.104883,
    "sol_amount": 0.133934545,
    "price_in_sol": 9.699356547877689e-08,
    "price_in_usd": 1.716786108974351e-05,
    "market_cap": 17167.86108974351,
    "signature": "3MUNrCwJHdBodPPZrAMB199ptGN5usE5k2oyg8WPDRidyMkoyYGSF9Rre8KUd29Tow9vfs1VrYPx1rY2FJkcGvJQ"
  },
  {
    "timestamp": 1730155012,
    "date": "2024-10-28 15:36:52",
    "token_amount": 530618.098379,
    "sol_amount": 0.063508768,
    "price_in_sol": 1.1968828088226673e-07,
    "price_in_usd": 2.118482571616121e-05,
    "market_cap": 21184.82571616121,
    "signature": "4PDgf5eU2gmYayBx2PKxcJTpWXN2vwz4k3KhbobjpW3QJ3j4CkD24i6xKBJuNMA1zQASAJRZ5Y26CUhC7Em9co4p"
  },
  {
    "timestamp": 1730155012,
    "date": "2024-10-28 15:36:52",
    "token_amount": 40762011.173184,
    "sol_amount": 1.71907328,
    "price_in_sol": 4.217341663286041e-08,
    "price_in_usd": 7.464694744016293e-06,
    "market_cap": 7464.694744016293,
    "signature": "65t3HiuUEkxH5AQtrRyWETk7NvZJUDXvs5PGbDVJAsGRCnivvirAL8wnhEkcq927AmEJxnxxgSc6wpF2tE1WUDCS"
  },
  {
    "timestamp": 1730155012,
    "date": "2024-10-28 15:36:52",
    "token_amount": 22412464.256277,
    "sol_amount": 1.79986628,
    "price_in_sol": 8.030648747140406e-08,
    "price_in_usd": 1.4214248282438518e-05,
    "market_cap": 14214.248282438519,
    "signature": "44qHyNGZBEnuB7D7YpQ6yHuH75TXXUGr5xEmYM2WpxQmqKWdS2xCn2za8EMwf9i1tZiduE8HRRqHCdPU7RZtEKUc"
  },
  {
    "timestamp": 1730155012,
    "date": "2024-10-28 15:36:52",
    "token_amount": 29571026.722925,
    "sol_amount": 1.75947328,
    "price_in_sol": 5.94999049740794e-08,
    "price_in_usd": 1.0531483180412054e-05,
    "market_cap": 10531.483180412053,
    "signature": "4u8WRFEF4kQNcJfher1FShMmq3RsYaGhqBEegHgMxRyCayeQLB4FvnCbTgcNmfgUP1yuFSzJrfUTFYmiiUYnFsVA"
  },
  {
    "timestamp": 1730155012,
    "date": "2024-10-28 15:36:52",
    "token_amount": 26511053.315994,
    "sol_amount": 0.76967328,
    "price_in_sol": 2.9032165219012992e-08,
    "price_in_usd": 5.1386932437653e-06,
    "market_cap": 5138.6932437653,
    "signature": "598dgyjmmnDF5BjR9vqQEuC179vmy3MTw21k6WqXYGH3srerDZJhdpdZKgGEqrve9uqTKpgNCXJPq7zr3TDRoT8V"
  }
]