[
  {
    "timestamp": 1730155144,
    "date": "2024-10-28 15:39:04",
    "token_amount": 20896334.764806,
    "sol_amount": 0.602465607,
    "price_in_sol": 2.8831161721943883e-08,
    "price_in_usd": 5.103115624784067e-06,
    "market_cap": 5103.115624784067,
    "signature": "5jyMuPvQZQpNLjSXHtPLVBBe7MF5nr3V9wm9ZCEpckxhN6gYrYortnZSHJpHpEs6c5W6saWjZ2quCTMJkrTv7aAL"
  },
  {
    "timestamp": 1730154991,
    "date": "2024-10-28 15:36:31",
    "token_amount": 1545983.984876,
    "sol_amount": 0.045530021,
    "price_in_sol": 2.9450512712556888e-08,
    "price_in_usd": 5.212740750122569e-06,
    "market_cap": 5212.740750122569,
    "signature": "5TRxozQXmCefKRtMbRDWeDv4dceXYWdJwgvQ8S6CX6KoakSoVHp4Y4fa2hFraNFmDiCnFtwd8eUiUvvm5BycdTPP"
  },
  {
    "timestamp": 1730154941,
    "date": "2024-10-28 15:35:41",
    "token_amount": 44565442.583984,
    "sol_amount": 1.372937248,
    "price_in_sol": 3.080721672207533e-08,
    "price_in_usd": 5.452877359807333e-06,
    "market_cap": 5452.877359807333,
    "signature": "3bkZGfpFQmhfjvSkdRc751airw5JZdYu3ZuL4mPJfiChCeAFQqcYBg8Ti8qXzRGvs4aatTtRji9oSJbWeabz5Cdc"
  },
  {
    "timestamp": 1730154939,
    "date": "2024-10-28 15:35:39",
    "token_amount": 4133041.170093,
    "sol_amount": 0.133552907,
    "price_in_sol": 3.231347124398348e-08,
    "price_in_usd": 5.719484410185076e-06,
    "market_cap": 5719.484410185076,
    "signature": "2GRUiVnzy6TqMkugvCNcNtdCP839MNvaZfCotRz58ZQcHkpHsrsVLzygMhHzND2X7qq1B1SmqMPZrLKRY54UXGmp"
  },
  {
    "timestamp": 1730154927,
    "date": "2024-10-28 15:35:27",
    "token_amount": 1725853.092569,
    "sol_amount": 0.056096919,
    "price_in_sol": 3.2503878366899433e-08,
    "price_in_usd": 5.7531864709412e-06,
    "market_cap": 5753.1864709412,
    "signature": "4ZjZijUWZqpdsCPkKAShbazs77jmgmvTsMmt6tjCwP4LhfEtS83xhDzqnP1ACLKv11zqK6zDMhEBCBtWRfwg6KEV"
  },
  {
    "timestamp": 1730154923,
    "date": "2024-10-28 15:35:23",
    "token_amount": 4466784.513765,
    "sol_amount": 0.146096153,
    "price_in_sol": 3.270723101814851e-08,
    "price_in_usd": 5.789179890212286e-06,
    "market_cap": 5789.179890212286,
    "signature": "3TtLSaC6sCSSh1YJzLSXPhZHi3fEzCph1duJzjbUjPs1jM465fzBFqWs7qiaGStq93YPvmicpe3Z182eUvHqmHEt"
  },
  {
    "timestamp": 1730154919,
    "date": "2024-10-28 15:35:19",
    "token_amount": 694687.700137,
    "sol_amount": 0.022839874,
    "price_in_sol": 3.287790181904146e-08,
    "price_in_usd": 5.819388621970339e-06,
    "market_cap": 5819.388621970339,
    "signature": "4C5MSANhepHBd5tmAF3NTygMvAcgw4picV5WCyCsTeK8M1UnB5rWD7VZTYdu6zx3v29nASbks2VJmqAQEacReiBX"
  },
  {
    "timestamp": 1730154916,
    "date": "2024-10-28 15:35:16",
    "token_amount": 22821455.158863,
    "sol_amount": 0.768581344,
    "price_in_sol": 3.367801652654527e-08,
    "price_in_usd": 5.961008925198513e-06,
    "market_cap": 5961.008925198513,
    "signature": "4BtWpTMyXM5q1mfF2JFBUZAyNgsqnLyc3LDS6sMfJavJYypyA2zzFDUEotQAhXAwN87DV2JuxJ2HQ9suoF8owVw"
  },
  {
    "timestamp": 1730154915,
    "date": "2024-10-28 15:35:15",
    "token_amount": 1725853.092569,
    "sol_amount": 0.066378116,
    "price_in_sol": 3.846104647365644e-08,
    "price_in_usd": 6.80760522583719e-06,
    "market_cap": 6807.60522583719,
    "signature": "1YBcMdnyhNLGMAGKqMQu5iBv8jYPRrPEQuwggjo9v584mPJPAoLzxvpMrR3Zosgur8MfXq7Br9g7Mdyd7oxP47W"
  },
  {
    "timestamp": 1730154915,
    "date": "2024-10-28 15:35:15",
    "token_amount": 5983586.273566,
    "sol_amount": 0.206818025,
    "price_in_sol": 3.4564225456841946e-08,
    "price_in_usd": 6.1178679058610245e-06,
    "market_cap": 6117.867905861024,
    "signature": "5XbusGKCxyAdd5gKK5ekkjobPfj6xzDGANSytzBbSZxHfZSXnjrD7Q4S8cUcWzdpowSUMWgfJ6gxg6wWqkVNTuqx"
  },
  {
    "timestamp": 1730154914,
    "date": "2024-10-28 15:35:14",
    "token_amount": 20215113.921073,
    "sol_amount": 0.718155668,
    "price_in_sol": 3.552567998399293e-08,
    "price_in_usd": 6.2880453571667485e-06,
    "market_cap": 6288.0453571667485,
    "signature": "2Vdjhcw7NRzt9j8mYA9sm6mDM45CS8qJzc6vxg1eUFp7kyP8Dkvo7F8ePB5CaDDGV24i3naJ4X9tFjuu8WSxxrp"
  },
  {
    "timestamp": 1730154914,
    "date": "2024-10-28 15:35:14",
    "token_amount": 13629670.265834,
    "sol_amount": 0.501858491,
    "price_in_sol": 3.6821029504875645e-08,
    "price_in_usd": 6.517322222362989e-06,
    "market_cap": 6517.322222362989,
    "signature": "5ZLD4vSH27Sbg25TNch3hkgHsJAeyFSJAqnHmB7HtwNK9AgM3ihhyEPFuq8VWPXYF9AcVWbu2sAN2xaSLAPzr4q8"
  },
  {
    "timestamp": 1730154912,
    "date": "2024-10-28 15:35:12",
    "token_amount": 43621174.32031,
    "sol_amount": 1.710128529,
    "price_in_sol": 3.9204091949532064e-08,
    "price_in_usd": 6.939124275067175e-06,
    "market_cap": 6939.124275067175,
    "signature": "2cKRGt7sPebguzmmZtmZDU9JZ4vWSjqdV7qw7xELVbiB6EXjsrqaetrxuY4f5dqr4AVGGci7r5mikGVVQL8UNYcn"
  },
  {
    "timestamp": 1730154911,
    "date": "2024-10-28 15:35:11",
    "token_amount": 4466784.513765,
    "sol_amount": 0.169632619,
    "price_in_sol": 3.797645005646773e-08,
    "price_in_usd": 6.721831659994788e-06,
    "market_cap": 6721.831659994788,
    "signature": "3dhq8BiFU2jSkKfsNPi7NjQKfGA5Tfg5XZLoJYxaALW7Xi2gqV5S59s7ZpTmHLzPTFgYoEUa9DgfMnqLT166BLBR"
  },
  {
    "timestamp": 1730154911,
    "date": "2024-10-28 15:35:11",
    "token_amount": 44565442.583984,
    "sol_amount": 1.809870147,
    "price_in_sol": 4.061151515749636e-08,
    "price_in_usd": 7.188238182876856e-06,
    "market_cap": 7188.238182876856,
    "signature": "66LcCaL23S6yudAGXj8aqmytu3GLnYYhcxbhRJCJueZ7Sj2qdvEtxnBqxeynYk9XVqMApi16Z8AUSCLe6UqbsqK9"
  },
  {
    "timestamp": 1730154910,
    "date": "2024-10-28 15:35:10",
    "token_amount": 41987001.330224,
    "sol_amount": 1.62359117,
    "price_in_sol": 3.866890033966944e-08,
    "price_in_usd": 6.844395360121491e-06,
    "market_cap": 6844.395360121491,
    "signature": "5e1CtEm5AdRYn4YJmRiohQYyq5ZUX3HFVs2pciZsfY85WbPnnH72pUoHxJeYUNUfLhS8Upf8AVUoFQtizAVJqzrT"
  },
  {
    "timestamp": 1730154910,
    "date": "2024-10-28 15:35:10",
    "token_amount": 21712266.123188,
    "sol_amount": 0.901067524,
    "price_in_sol": 4.150039055746875e-08,
    "price_in_usd": 7.345569128671969e-06,
    "market_cap": 7345.569128671969,
    "signature": "2qYDq5Cqq9yFooNzfPE4Kwv6h9Mp7QgmQ8twHEio5F2dxSPy7dVTpPynoLW7eRB8WHjFE6x355gycaktooLsSe2t"
  },
  {
    "timestamp": 1730154907,
    "date": "2024-10-28 15:35:07",
    "token_amount": 17902642.76874,
    "sol_amount": 0.770098901,
    "price_in_sol": 4.30159340689453e-08,
    "price_in_usd": 7.613820330203317e-06,
    "market_cap": 7613.820330203317,
    "signature": "5EgkwJ8vBSVghi7ZGibrQ1c4FNw4FfWwJuAqBQYTJa4n5Ln8c1aGG1CzrocWCAku2oPqyN69eXFsjB19UfgbUJNg"
  },
  {
    "timestamp": 1730154907,
    "date": "2024-10-28 15:35:07",
    "token_amount": 4133041.170093,
    "sol_amount": 0.183138236,
    "price_in_sol": 4.4310769833410376e-08,
    "price_in_usd": 7.843006260513637e-06,
    "market_cap": 7843.006260513637,
    "signature": "2RgUw3Ux6HoCsdbgru9scsz5N7rdKZFMHMh7ZxZMvBio7EZyQGdX4EtbB9G79QVAUThm7k2s3GPeqyegC9AswKbU"
  },
  {
    "timestamp": 1730154907,
    "date": "2024-10-28 15:35:07",
    "token_amount": 108811607.173978,
    "sol_amount": 5.474248773,
    "price_in_sol": 5.030941932736337e-08,
    "price_in_usd": 8.904767220943318e-06,
    "market_cap": 8904.767220943319,
    "signature": "5yJFk2E58xV7e29maUAaxyMqVvWGeb9rsC822hUWBk3N86zzX7MK1VtjtWjZb3yvsCTV9FmaSErY3aaxJbVXqqG2"
  },
  {
    "timestamp": 1730154906,
    "date": "2024-10-28 15:35:06",
    "token_amount": 36330480.081486,
    "sol_amount": 2.200875311,
    "price_in_sol": 6.057930712899015e-08,
    "price_in_usd": 1.0722537361831258e-05,
    "market_cap": 10722.537361831257,
    "signature": "v87xqN9sebhbYtvHcBUxQDFCD2gMXcidHntLBEFR5TL4BDNNC5jj3fTDSEYLzWFkTHDV3kR9LZZJ9HudgN1Ep7d"
  },
  {
    "timestamp": 1730154906,
    "date": "2024-10-28 15:35:06",
    "token_amount": 13629670.265834,
    "sol_amount": 0.893101584,
    "price_in_sol": 6.552627954901967e-08,
    "price_in_usd": 1.1598151480176482e-05,
    "market_cap": 11598.151480176482,
    "signature": "4RY9xwutwCzmAVLjSoKV4E84Y2PbLDnW1DmzQcAnfEJef8GJNZ5pCLFcuj3wKA8mBaux9yhb6GjkuCJjKB1hLJaq"
  },
  {
    "timestamp": 1730154905,
    "date": "2024-10-28 15:35:05",
    "token_amount": 1063171.265886,
    "sol_amount": 0.065270234,
    "price_in_sol": 6.139202223980976e-08,
    "price_in_usd": 1.0866387936446327e-05,
    "market_cap": 10866.387936446326,
    "signature": "28aSgpZrnoFu1HX9ceU5FSLsjpw1mozrzG7kugtWyhtkk8ZR4HGcBm3xtNXrNjuHWhAQfL3w13YdnTRDqbNpcqwA"
  },
  {
    "timestamp": 1730154904,
    "date": "2024-10-28 15:35:04",
    "token_amount": 66292860.616627,
    "sol_amount": 4.486915185,
    "price_in_sol": 6.768323380926228e-08,
    "price_in_usd": 1.1979932384239423e-05,
    "market_cap": 11979.932384239422,
    "signature": "366JB9LXTUuuWTDBLgbBiGLhFf3wJvgte58MVLAYWaef21fPMCzmbCSuULWD1oFFBUGpeWi4vkdzkoRF4CmbKeAR"
  },
  {
    "timestamp": 1730154904,
    "date": "2024-10-28 15:35:04",
    "token_amount": 41987001.330224,
    "sol_amount": 3.062044279,
    "price_in_sol": 7.29283869290235e-08,
    "price_in_usd": 1.290832448643716e-05,
    "market_cap": 12908.324486437159,
    "signature": "HsoDR5zNDh2rHfEXfbSWGGhyrgjbDNktiJS7SC1DHcrf7Mf661d7oZHJmkPbu3ynSDzGSgvJADqNdY9D8oJS6Sx"
  },
  {
    "timestamp": 1730154902,
    "date": "2024-10-28 15:35:02",
    "token_amount": 31263551.081661,
    "sol_amount": 2.154419617,
    "price_in_sol": 6.891154531270661e-08,
    "price_in_usd": 1.219734352034907e-05,
    "market_cap": 12197.34352034907,
    "signature": "37adiWNpdrwadKKj5MYuzkQfQecqHwmEeVuyQEPJyGmGinCXHEstu3MBL4Rboayj5yU3qLeE8V9XKZUx1ALJuU55"
  },
  {
    "timestamp": 1730154901,
    "date": "2024-10-28 15:35:01",
    "token_amount": 1545983.984876,
    "sol_amount": 0.157681109,
    "price_in_sol": 1.0199401193192002e-07,
    "price_in_usd": 1.805294011194984e-05,
    "market_cap": 18052.94011194984,
    "signature": "5Uv2GPF1YeinqxQg33huVqiZUvmpbsNYFYUtHWqDH7FjLw1GFffiDngp4v86cfnfZpCaDmzaYyJHJoNgsdQRQhc2"
  },
  {
    "timestamp": 1730154900,
    "date": "2024-10-28 15:35:00",
    "token_amount": 43621174.32031,
    "sol_amount": 3.102044279,
    "price_in_sol": 7.111326843751865e-08,
    "price_in_usd": 1.25870485134408e-05,
    "market_cap": 12587.048513440799,
    "signature": "3NjGjhk6UTxWcj3BuTeixrc9Zs6eWhvMpE1R2zruViYUgedGJ2M9PPLzYtfeLF1T3CvDwuvN2z2UJrugM3UyQ6yn"
  },
  {
    "timestamp": 1730154898,
    "date": "2024-10-28 15:34:58",
    "token_amount": 68505079.63367,
    "sol_amount": 4.796324456,
    "price_in_sol": 7.001414320877051e-08,
    "price_in_usd": 1.239250334795238e-05,
    "market_cap": 12392.50334795238,
    "signature": "2wCpcpgTLuAWNxKbM4mrdUqAEK8zz9tS223Yrd4J4T5GMFC3ynr3ZxQbLx3QUF7pv159N3jVBrpbDDXAAyS5NVVW"
  },
  {
    "timestamp": 1730154897,
    "date": "2024-10-28 15:34:57",
    "token_amount": 47039051.512557,
    "sol_amount": 4.362133138,
    "price_in_sol": 9.273429199216603e-08,
    "price_in_usd": 1.6413969682613387e-05,
    "market_cap": 16413.969682613388,
    "signature": "B1Ydi3H1xZHHfdynvz8GWKzCnPBNvTo9Re3w8UPR3bioJ9mzXpDJVb9wEH9VWYV97pw5SvGh5d8WycyNfCpbz9J"
  },
  {
    "timestamp": 1730154897,
    "date": "2024-10-28 15:34:57",
    "token_amount": 31512874.100648,
    "sol_amount": 2.566244609,
    "price_in_sol": 8.143480029158084e-08,
    "price_in_usd": 1.4413959651609808e-05,
    "market_cap": 14413.959651609808,
    "signature": "cErH1Wgu33edzsGLCQPcPVSetr8gjZy9PzxDLH5FroGjrJ8E9DvTo2Y7bjogNJs3XSAuz3rP4skTnCSNzxyWBoE"
  },
  {
    "timestamp": 1730154896,
    "date": "2024-10-28 15:34:56",
    "token_amount": 20215113.921073,
    "sol_amount": 2.042044279,
    "price_in_sol": 1.0101571957362535e-07,
    "price_in_usd": 1.7879782364531686e-05,
    "market_cap": 17879.782364531686,
    "signature": "2YJTT9m1MkyaecYvym3tb1XazeR4LrRmv2q5FmETx24y6uByXQffk9Wd1mnptuCgATez4cNoFnrStQFADtkqeq4j"
  },
  {
    "timestamp": 1730154896,
    "date": "2024-10-28 15:34:56",
    "token_amount": 21712266.123188,
    "sol_amount": 2.062044279,
    "price_in_sol": 9.497139853116499e-08,
    "price_in_usd": 1.6809937540016204e-05,
    "market_cap": 16809.937540016203,
    "signature": "RaxPohiza3vxERcD8z8UoLbmbDvNV4xPfqyz9Kz8fnyDFJPSznidBRtcz8ri7WyKu1sALwGJqXtwm3CFRY4Kiz2"
  },
  {
    "timestamp": 1730154896,
    "date": "2024-10-28 15:34:56",
    "token_amount": 5346654.140659,
    "sol_amount": 0.469639838,
    "price_in_sol": 8.783808072203352e-08,
    "price_in_usd": 1.5547340287799934e-05,
    "market_cap": 15547.340287799934,
    "signature": "3RVtGa7BZcgwodufFGNL7P6NsVJMhcqsXZsAMGHLF5bZKz7MrYqXos15scoCdYYdaFEvg9nR6YP42gyzvCaUWgLf"
  },
  {
    "timestamp": 1730154896,
    "date": "2024-10-28 15:34:56",
    "token_amount": 5983586.273566,
    "sol_amount": 0.530758454,
    "price_in_sol": 8.87023984837921e-08,
    "price_in_usd": 1.5700324531631202e-05,
    "market_cap": 15700.324531631202,
    "signature": "4ryaCwTNm8TSorRREmWgHy2VLUo4GQhhK5btKQF7bdUFMVJkUnaP4GewYkNGLqYFzBBhQyCAQ1iaghEuEyYgTp5V"
  },
  {
    "timestamp": 1730154896,
    "date": "2024-10-28 15:34:56",
    "token_amount": 1063171.265886,
    "sol_amount": 0.103034245,
    "price_in_sol": 9.691217991499781e-08,
    "price_in_usd": 1.7153455844954614e-05,
    "market_cap": 17153.455844954613,
    "signature": "3LpePQFDjR3qN7tdpB8LvGQxoUV5TDCHcQPdX96WRvejBod9oLXaMtdQgSf6ZzcheHhdj97LjnsM43KBzejJeTRH"
  },
  {
    "timestamp": 1730154893,
    "date": "2024-10-28 15:34:53",
    "token_amount": 40161353.846207,
    "sol_amount": 3.722381874,
    "price_in_sol": 9.268566712801582e-08,
    "price_in_usd": 1.64053630816588e-05,
    "market_cap": 16405.3630816588,
    "signature": "5Q98DAZZiDntq8qYy7L4MWoKT5xLzoAHpA8SFDWmRBaQzfR4m5DochGzCnpt2GgAUucQXmixkeJiwNP9UvnyM2np"
  },
  {
    "timestamp": 1730154892,
    "date": "2024-10-28 15:34:52",
    "token_amount": 31263551.081661,
    "sol_amount": 3.082044279,
    "price_in_sol": 9.85826680708676e-08,
    "price_in_usd": 1.7449132248543566e-05,
    "market_cap": 17449.132248543567,
    "signature": "5j51YPdxiUAYmoaiZAXDArw27HZNy3T7xuXHJbhN4vd47Bbg79XauD1EowdMaHHfpjN3mja9MLxot3JsJbWC1dAT"
  },
  {
    "timestamp": 1730154892,
    "date": "2024-10-28 15:34:52",
    "token_amount": 22821455.158863,
    "sol_amount": 2.072044279,
    "price_in_sol": 9.079369674616455e-08,
    "price_in_usd": 1.6070484324071127e-05,
    "market_cap": 16070.484324071127,
    "signature": "3PV31hCmJb4o7R2AU3tbLWFhw8UydUnEqti3Cu8ADAWSHP15Lh2TW1NpuuwHyrXJpPrVPr8m4eCv18VYahUogjyU"
  },
  {
    "timestamp": 1730154892,
    "date": "2024-10-28 15:34:52",
    "token_amount": 22902960.18912,
    "sol_amount": 2.022004999,
    "price_in_sol": 8.828574919151931e-08,
    "price_in_usd": 1.5626577606898918e-05,
    "market_cap": 15626.577606898918,
    "signature": "2k1MyQXEVeLk7iJsHU38KksayRW7PG7REUjjrWfYVYyz1BzU8zSHmuP7EBZLsGGtUg3g8mNkWfktWc5cG5BXRzCY"
  },
  {
    "timestamp": 1730154892,
    "date": "2024-10-28 15:34:52",
    "token_amount": 21769483.0,
    "sol_amount": 1.866761763,
    "price_in_sol": 8.575131357046926e-08,
    "price_in_usd": 1.517798250197306e-05,
    "market_cap": 15177.98250197306,
    "signature": "4cq5HeyfT5xwxca2fTvaLitNvYeC3df7xh7ZqZqjzNtX1hyJ9eCfMRN2D1ZwL7TNX2NBosg6nQ8nCzuzMcVmUBiY"
  },
  {
    "timestamp": 1730154892,
    "date": "2024-10-28 15:34:52",
    "token_amount": 694687.700137,
    "sol_amount": 0.066044279,
    "price_in_sol": 9.507045970005709e-08,
    "price_in_usd": 1.6827471366910104e-05,
    "market_cap": 16827.471366910104,
    "signature": "43fgmyNBRmjUP7wk72AfrEzVXzimn7rwXjWGFFeFRfnsFYENYUyNszFsJRegfpDTfEEiLM6ryRWBhUBAVyskj3vy"
  },
  {
    "timestamp": 1730154892,
    "date": "2024-10-28 15:34:52",
    "token_amount": 8523850.0,
    "sol_amount": 0.7125821,
    "price_in_sol": 8.359862034174697e-08,
    "price_in_usd": 1.4796955800489215e-05,
    "market_cap": 14796.955800489215,
    "signature": "2s3AvFCtSSXF6py8hBcSHQ7dkTXv1KNu3UMXxUsAfZ2qcGUtaWabhstCRqkxhpKDxeLt1mXDAZDUHwHPqJE5zLkS"
  },
  {
    "timestamp": 1730154891,
    "date": "2024-10-28 15:34:51",
    "token_amount": 8358533.905922,
    "sol_amount": 0.71653955,
    "price_in_sol": 8.572550617906012e-08,
    "price_in_usd": 1.5173414593693642e-05,
    "market_cap": 15173.414593693642,
    "signature": "2gDnJymCXgkmWHQ1321xWPn9VTj29guCcbqp9voLuU5gPe5tLEXUkJuiVGCSPmhkSYHsm9f25ZiFfK7pWRjcDDaA"
  },
  {
    "timestamp": 1730154891,
    "date": "2024-10-28 15:34:51",
    "token_amount": 36330480.081486,
    "sol_amount": 4.422044279,
    "price_in_sol": 1.2171719914192578e-07,
    "price_in_usd": 2.1543944248120862e-05,
    "market_cap": 21543.94424812086,
    "signature": "4DCNrfHDGShNRfRgLfDeN6V55bMyz2p5Hq7EmHGj3ArW9rMXZ7kaJQ3Lgp3bL4PzMyZHK1VEyHbLyzY2LZ9Ss3Db"
  },
  {
    "timestamp": 1730154891,
    "date": "2024-10-28 15:34:51",
    "token_amount": 80332955.724609,
    "sol_amount": 8.042745852,
    "price_in_sol": 1.0011763888747597e-07,
    "price_in_usd": 1.7720822083083248e-05,
    "market_cap": 17720.822083083247,
    "signature": "21UYXZ4dJAFzJNZgwGWcSkaVDAmCiwg5qA2mKuqGu7XLaWNvHXVLrtJiKooyEMETEWJwZANqgkeW6Fh8yUXiP5ks"
  },
  {
    "timestamp": 1730154891,
    "date": "2024-10-28 15:34:51",
    "token_amount": 85080202.761524,
    "sol_amount": 7.540681499,
    "price_in_sol": 8.863027184051491e-08,
    "price_in_usd": 1.568755811577114e-05,
    "market_cap": 15687.558115771139,
    "signature": "3ja1LKHvf5uNeSfFi9oqTWjfqxUvWv7t4WTFuqtHfM39mDXwR8JyRA1HJk66gS51GzLj85r4K4eKrYSMx5N4432z"
  },
  {
    "timestamp": 1730154891,
    "date": "2024-10-28 15:34:51",
    "token_amount": 52301868.431226,
    "sol_amount": 4.33780373,
    "price_in_sol": 8.293783492083015e-08,
    "price_in_usd": 1.4679996780986938e-05,
    "market_cap": 14679.996780986938,
    "signature": "1RZznR7BrSBkXhNMArrf1JvLqC1nv4dy9fnxfYPrbRvB9Xvy5PLsiGuCeGVpse3G3vTvRsM1sRYnwbwNEdMHVYD"
  },
  {
    "timestamp": 1730154890,
    "date": "2024-10-28 15:34:50",
    "token_amount": 34612903.0,
    "sol_amount": 3.301653256,
    "price_in_sol": 9.538793252909182e-08,
    "price_in_usd": 1.6883664057649253e-05,
    "market_cap": 16883.664057649254,
    "signature": "SgR2UFBBzjgRk1unvrPfi9jYzLo915GQSLbZ6ZRiedF3RGS8jX8S1PoMZyZoqQeuqrenFDA5NyHFhSGwz3gBrp6"
  },
  {
    "timestamp": 1730154890,
    "date": "2024-10-28 15:34:50",
    "token_amount": 1088685.649461,
    "sol_amount": 0.117044279,
    "price_in_sol": 1.0750971050086656e-07,
    "price_in_usd": 1.902921875865338e-05,
    "market_cap": 19029.21875865338,
    "signature": "3HKfwC1oTHGfQVVjSedW9waYYmaifVLA9u1duHJTqkQhBtC61hGC5hdne59pUrsRRVBEn7KSfPfPZegCNrG6y3M5"
  },
  {
    "timestamp": 1730154889,
    "date": "2024-10-28 15:34:49",
    "token_amount": 30622174.212901,
    "sol_amount": 3.070004999,
    "price_in_sol": 1.0025431171724636e-07,
    "price_in_usd": 1.7745013173952604e-05,
    "market_cap": 17745.013173952604,
    "signature": "XdXWnuRxRyHFZHCWGve7vjKvkPdW7TMpJ5VW9Ki8HLi8wr3s3ReJdS6aFHtp97pYyrmGcoHMMNJABjzR47hm1mq"
  },
  {
    "timestamp": 1730154887,
    "date": "2024-10-28 15:34:47",
    "token_amount": 21769483.0,
    "sol_amount": 1.942933781,
    "price_in_sol": 8.925034099339888e-08,
    "price_in_usd": 1.57973103558316e-05,
    "market_cap": 15797.310355831602,
    "signature": "WcvSNwQ2nXX3WmJSwyga5EXoCy4VYrA8ko6864S7uWgLw9Bn7avPsqbd1GGcDNWHgYhRLoJUErkck5XYaHJY9dX"
  },
  {
    "timestamp": 1730154887,
    "date": "2024-10-28 15:34:47",
    "token_amount": 36762547.447428,
    "sol_amount": 3.070004999,
    "price_in_sol": 8.350903874086084e-08,
    "price_in_usd": 1.4781099857132369e-05,
    "market_cap": 14781.099857132369,
    "signature": "4Yb3GCs5RYCGNkgjW7Jz1mmwDNXQ6ShW1HoZ2ACPT2VaiFUwoFLKPMxYg5eH1fCiBWhCSfJzKE3KxM3mPfSpdien"
  },
  {
    "timestamp": 1730154887,
    "date": "2024-10-28 15:34:47",
    "token_amount": 41426885.513649,
    "sol_amount": 3.072044279,
    "price_in_sol": 7.415581067487797e-08,
    "price_in_usd": 1.31255784894534e-05,
    "market_cap": 13125.578489453399,
    "signature": "5Vz3fPtVZyWeoZQgi6yeFp9TBq3Q41W9uLyvfendzf5v6x4nzik2oz1eBhEbkVZS5nLcsVa9bpuhFneCBpgZFrpg"
  },
  {
    "timestamp": 1730154887,
    "date": "2024-10-28 15:34:47",
    "token_amount": 47039051.512557,
    "sol_amount": 3.082044279,
    "price_in_sol": 6.552096991533202e-08,
    "price_in_usd": 1.1597211675013767e-05,
    "market_cap": 11597.211675013767,
    "signature": "2jx8NV8XbtJ8LUAoH2tz1kQS6V4s9HxUJXCWq3VBCoCRc8jyEfdoKHtzB9dDN2LeKjNtCB6szDxKLgdmTq2RGagS"
  },
  {
    "timestamp": 1730154886,
    "date": "2024-10-28 15:34:46",
    "token_amount": 5346654.140659,
    "sol_amount": 0.316447556,
    "price_in_sol": 5.918609052969272e-08,
    "price_in_usd": 1.0475938023755611e-05,
    "market_cap": 10475.93802375561,
    "signature": "4sstEVnbZMZPVrUS7JDPFqdSV3XVZkFT8zamgiEtbBD6CF5xL7YKUbPB43sKwxynAhSgBh4AMacD8nLhZD39e59a"
  },
  {
    "timestamp": 1730154886,
    "date": "2024-10-28 15:34:46",
    "token_amount": 17902642.76874,
    "sol_amount": 1.027490256,
    "price_in_sol": 5.7393216703966865e-08,
    "price_in_usd": 1.0158599356602135e-05,
    "market_cap": 10158.599356602135,
    "signature": "3gQepasNB5XZzj6Yjn49QWvLQKZKfq1tbLEwit5JwEV1YaoaTpfmd9Kc6EdE9KthyNsq9TwEz8zXftcRiBhTETCu"
  },
  {
    "timestamp": 1730154885,
    "date": "2024-10-28 15:34:45",
    "token_amount": 31512874.100648,
    "sol_amount": 1.69959649,
    "price_in_sol": 5.3933401459089736e-08,
    "price_in_usd": 9.546212058258883e-06,
    "market_cap": 9546.212058258883,
    "signature": "2UfGA78UVRHCMovjdGxPqCRPzFvftpNvFDohTeXUbPsjh14unCNcyvBU4FwATy7q3WDRUpEEf68b67nb2DBa3Pfw"
  },
  {
    "timestamp": 1730154885,
    "date": "2024-10-28 15:34:45",
    "token_amount": 8523850.0,
    "sol_amount": 0.444512957,
    "price_in_sol": 5.214931715128727e-08,
    "price_in_usd": 9.230429135777847e-06,
    "market_cap": 9230.429135777846,
    "signature": "63ytA5t65aMULBwfG6rEgpZ3rhVNu7gK1ab1MgNW55MLr7gbS9rtbzSeZeD9gSGfKUAwYA1VQyNPwuQtdoMa6kYQ"
  },
  {
    "timestamp": 1730154884,
    "date": "2024-10-28 15:34:44",
    "token_amount": 12537800.858883,
    "sol_amount": 0.633014556,
    "price_in_sol": 5.048848383578455e-08,
    "price_in_usd": 8.936461638933866e-06,
    "market_cap": 8936.461638933866,
    "signature": "5R3d7N44hEjeLrB7dx3T222enJZQJdgvm5dpkzxGRd2q1kWnbkbMaESDcqXEzccdMhte86PtgvfBd6LvTNGC3ZDr"
  },
  {
    "timestamp": 1730154883,
    "date": "2024-10-28 15:34:43",
    "token_amount": 40161353.846207,
    "sol_amount": 2.052044279,
    "price_in_sol": 5.109499761532076e-08,
    "price_in_usd": 9.043814577911775e-06,
    "market_cap": 9043.814577911775,
    "signature": "nKR6BFBa7w4jgE4S6NKf3htKNXafRCDsAmK7Vh8aBcpUQTuR8UWxx3uDTAHAPXyUYqrm4Eh5yoeLxBbXvoGTPXi"
  },
  {
    "timestamp": 1730154883,
    "date": "2024-10-28 15:34:43",
    "token_amount": 68505079.63367,
    "sol_amount": 3.102044279,
    "price_in_sol": 4.528196004716935e-08,
    "price_in_usd": 8.014906928348974e-06,
    "market_cap": 8014.906928348974,
    "signature": "4HfVqg9Hq84XPkiqZRPp5aPCFAd3TCK2RQ88BxGs9zc5ickPby1M8xkPYzkoqiCduetXYxU56SP9NRB3NkoycJHH"
  },
  {
    "timestamp": 1730154882,
    "date": "2024-10-28 15:34:42",
    "token_amount": 52301868.431226,
    "sol_amount": 2.072184279,
    "price_in_sol": 3.9619698897082526e-08,
    "price_in_usd": 7.012686704783607e-06,
    "market_cap": 7012.686704783607,
    "signature": "4ZicCptpnLEWEHhQuvqaTLjLMrHmaY8HNDebcpFjiSWCAwGkzKPGxr3n14KYxEE931Jr6L3x4rzVJyBJVEoDfZNW"
  },
  {
    "timestamp": 1730154879,
    "date": "2024-10-28 15:34:39",
    "token_amount": 43389900.427507,
    "sol_amount": 1.524044279,
    "price_in_sol": 3.512440139258382e-08,
    "price_in_usd": 6.217019046487336e-06,
    "market_cap": 6217.019046487336,
    "signature": "2p1eqgMq8w9kNkFfP37STTt8NDPmJ2MhGDGA8Aa71yVqXuVbTXTdHxRs1L9PREjE48V29sjuW5XThpWRSxcRu7eC"
  },
  {
    "timestamp": 1730154878,
    "date": "2024-10-28 15:34:38",
    "token_amount": 41792669.529611,
    "sol_amount": 1.31567428,
    "price_in_sol": 3.148098206714976e-08,
    "price_in_usd": 5.5721338258855075e-06,
    "market_cap": 5572.133825885508,
    "signature": "8ky3kyasjkX3dHZfAgBRfnGBWEkcWHbRnkB387crUhU7EUaScvRaK6CnbMRBPpiGkPUwWDU9vvyHqmcLibQTFRf"
  },
  {
    "timestamp": 1730154878,
    "date": "2024-10-28 15:34:38",
    "token_amount": 1000000000.0,
    "sol_amount": 1.00123192,
    "price_in_sol": 1.00123192e-09,
    "price_in_usd": 1.7721804984e-07,
    "market_cap": 177.21804984,
    "signature": "33tfHWMadXoLKzG7utavKFxWpddUU7VWLJa3ix158E5ZBrUSrSf8YXiUQtY328jsEFwyRZHFNEqaK1Nzq5eQhdU7"
  }
]